{
"meta":{"test_sets":[],"test_metrics":[],"learn_metrics":[{"best_value":"Min","name":"Logloss"}],"launch_mode":"Train","parameters":"","iteration_count":1000,"learn_sets":["learn"],"name":"experiment"},
"iterations":[
{"learn":[0.6648240384],"iteration":0,"passed_time":0.01806073401,"remaining_time":18.04267327},
{"learn":[0.6409772466],"iteration":1,"passed_time":0.0371165786,"remaining_time":18.52117272},
{"learn":[0.6153030489],"iteration":2,"passed_time":0.05472419367,"remaining_time":18.1866737},
{"learn":[0.5974493037],"iteration":3,"passed_time":0.07096696713,"remaining_time":17.67077482},
{"learn":[0.576962003],"iteration":4,"passed_time":0.08732625242,"remaining_time":17.37792423},
{"learn":[0.5612977208],"iteration":5,"passed_time":0.1040807238,"remaining_time":17.24270658},
{"learn":[0.547245666],"iteration":6,"passed_time":0.1200780915,"remaining_time":17.03393497},
{"learn":[0.5339419565],"iteration":7,"passed_time":0.1374788791,"remaining_time":17.04738101},
{"learn":[0.5214712273],"iteration":8,"passed_time":0.1536455394,"remaining_time":16.91808106},
{"learn":[0.5098208437],"iteration":9,"passed_time":0.1709217145,"remaining_time":16.92124973},
{"learn":[0.4992683945],"iteration":10,"passed_time":0.1869111108,"remaining_time":16.80500805},
{"learn":[0.4900325671],"iteration":11,"passed_time":0.207261445,"remaining_time":17.06452564},
{"learn":[0.4825918233],"iteration":12,"passed_time":0.2242855547,"remaining_time":17.02844942},
{"learn":[0.4756698407],"iteration":13,"passed_time":0.2413171618,"remaining_time":16.99562297},
{"learn":[0.4703953958],"iteration":14,"passed_time":0.2588683818,"remaining_time":16.99902374},
{"learn":[0.4649048009],"iteration":15,"passed_time":0.275678755,"remaining_time":16.95424343},
{"learn":[0.4604544935],"iteration":16,"passed_time":0.2926016543,"remaining_time":16.91926037},
{"learn":[0.4555355166],"iteration":17,"passed_time":0.3074000033,"remaining_time":16.77037796},
{"learn":[0.4518168043],"iteration":18,"passed_time":0.3222666445,"remaining_time":16.6391357},
{"learn":[0.4476713304],"iteration":19,"passed_time":0.3386584184,"remaining_time":16.5942625},
{"learn":[0.4443141204],"iteration":20,"passed_time":0.3552427787,"remaining_time":16.56108002},
{"learn":[0.4398868895],"iteration":21,"passed_time":0.3725478266,"remaining_time":16.56144429},
{"learn":[0.4362619378],"iteration":22,"passed_time":0.3886327863,"remaining_time":16.50844488},
{"learn":[0.433106539],"iteration":23,"passed_time":0.4052607628,"remaining_time":16.48060435},
{"learn":[0.4305895994],"iteration":24,"passed_time":0.4204723261,"remaining_time":16.39842072},
{"learn":[0.4284743801],"iteration":25,"passed_time":0.4344594628,"remaining_time":16.27551987},
{"learn":[0.4260497503],"iteration":26,"passed_time":0.4491089104,"remaining_time":16.18455444},
{"learn":[0.4240759342],"iteration":27,"passed_time":0.4646648379,"remaining_time":16.13050794},
{"learn":[0.4216561617],"iteration":28,"passed_time":0.4778015333,"remaining_time":15.99811341},
{"learn":[0.4203534915],"iteration":29,"passed_time":0.4976966344,"remaining_time":16.09219118},
{"learn":[0.4180120096],"iteration":30,"passed_time":0.5103202613,"remaining_time":15.95162365},
{"learn":[0.4164881846],"iteration":31,"passed_time":0.5237133935,"remaining_time":15.84233015},
{"learn":[0.414994862],"iteration":32,"passed_time":0.5380157913,"remaining_time":15.76549304},
{"learn":[0.413724938],"iteration":33,"passed_time":0.5518042887,"remaining_time":15.67773361},
{"learn":[0.4126267905],"iteration":34,"passed_time":0.5635321877,"remaining_time":15.53738746},
{"learn":[0.4113181591],"iteration":35,"passed_time":0.5769918795,"remaining_time":15.45056033},
{"learn":[0.4098801827],"iteration":36,"passed_time":0.5916081914,"remaining_time":15.39780239},
{"learn":[0.4087978007],"iteration":37,"passed_time":0.6075913895,"remaining_time":15.3816557},
{"learn":[0.4078390605],"iteration":38,"passed_time":0.6244675912,"remaining_time":15.38752193},
{"learn":[0.4067708839],"iteration":39,"passed_time":0.6399212697,"remaining_time":15.35811047},
{"learn":[0.4060853816],"iteration":40,"passed_time":0.6544963637,"remaining_time":15.30882958},
{"learn":[0.4053301919],"iteration":41,"passed_time":0.6707695762,"remaining_time":15.29993462},
{"learn":[0.4042281081],"iteration":42,"passed_time":0.6859419275,"remaining_time":15.26619592},
{"learn":[0.4034695381],"iteration":43,"passed_time":0.7006014179,"remaining_time":15.22215808},
{"learn":[0.4027864626],"iteration":44,"passed_time":0.7171750086,"remaining_time":15.2200474},
{"learn":[0.402112527],"iteration":45,"passed_time":0.7319358219,"remaining_time":15.17971248},
{"learn":[0.401571956],"iteration":46,"passed_time":0.7434032631,"remaining_time":15.07368744},
{"learn":[0.4007875398],"iteration":47,"passed_time":0.7567561581,"remaining_time":15.00899714},
{"learn":[0.3998835365],"iteration":48,"passed_time":0.7711192307,"remaining_time":14.96600793},
{"learn":[0.3993753363],"iteration":49,"passed_time":0.7855802011,"remaining_time":14.92602382},
{"learn":[0.3989442347],"iteration":50,"passed_time":0.7993414576,"remaining_time":14.87402046},
{"learn":[0.3984308855],"iteration":51,"passed_time":0.8280037541,"remaining_time":15.09514536},
{"learn":[0.397650204],"iteration":52,"passed_time":0.8416161186,"remaining_time":15.03793329},
{"learn":[0.3971724469],"iteration":53,"passed_time":0.8564662509,"remaining_time":15.00401988},
{"learn":[0.3968513807],"iteration":54,"passed_time":0.8739033372,"remaining_time":15.01524825},
{"learn":[0.3964357879],"iteration":55,"passed_time":0.8874490724,"remaining_time":14.95985579},
{"learn":[0.3958817072],"iteration":56,"passed_time":0.9075483134,"remaining_time":15.01435192},
{"learn":[0.395073325],"iteration":57,"passed_time":0.9241338174,"remaining_time":15.00920786},
{"learn":[0.3947668063],"iteration":58,"passed_time":0.9403256698,"remaining_time":14.99739755},
{"learn":[0.3940362535],"iteration":59,"passed_time":0.9568183246,"remaining_time":14.99015375},
{"learn":[0.3937259871],"iteration":60,"passed_time":0.973126719,"remaining_time":14.97977031},
{"learn":[0.393340206],"iteration":61,"passed_time":0.9895924709,"remaining_time":14.97157641},
{"learn":[0.3930560467],"iteration":62,"passed_time":1.009203285,"remaining_time":15.00989648},
{"learn":[0.3927871143],"iteration":63,"passed_time":1.026408711,"remaining_time":15.0112274},
{"learn":[0.3924310175],"iteration":64,"passed_time":1.042471799,"remaining_time":14.99555587},
{"learn":[0.3921093909],"iteration":65,"passed_time":1.057434789,"remaining_time":14.96430444},
{"learn":[0.3915519396],"iteration":66,"passed_time":1.071318623,"remaining_time":14.91851157},
{"learn":[0.391495836],"iteration":67,"passed_time":1.081746856,"remaining_time":14.82629514},
{"learn":[0.3912105794],"iteration":68,"passed_time":1.094657763,"remaining_time":14.7699475},
{"learn":[0.3906786641],"iteration":69,"passed_time":1.109241192,"remaining_time":14.73706155},
{"learn":[0.3902722302],"iteration":70,"passed_time":1.121852159,"remaining_time":14.67888248},
{"learn":[0.3898064819],"iteration":71,"passed_time":1.137355779,"remaining_time":14.65925226},
{"learn":[0.3896895694],"iteration":72,"passed_time":1.151183532,"remaining_time":14.6184539},
{"learn":[0.3894164949],"iteration":73,"passed_time":1.167509055,"remaining_time":14.60964034},
{"learn":[0.3892644334],"iteration":74,"passed_time":1.180646507,"remaining_time":14.56130692},
{"learn":[0.3886913097],"iteration":75,"passed_time":1.19607054,"remaining_time":14.54169973},
{"learn":[0.3882433921],"iteration":76,"passed_time":1.217130027,"remaining_time":14.58975344},
{"learn":[0.3879965964],"iteration":77,"passed_time":1.233329918,"remaining_time":14.5785921},
{"learn":[0.387787656],"iteration":78,"passed_time":1.25007944,"remaining_time":14.57371094},
{"learn":[0.3876709157],"iteration":79,"passed_time":1.265464188,"remaining_time":14.55283816},
{"learn":[0.3873367376],"iteration":80,"passed_time":1.279863612,"remaining_time":14.52092172},
{"learn":[0.3868250651],"iteration":81,"passed_time":1.295659958,"remaining_time":14.50507124},
{"learn":[0.3864885883],"iteration":82,"passed_time":1.3106432,"remaining_time":14.48023873},
{"learn":[0.3861382471],"iteration":83,"passed_time":1.32699805,"remaining_time":14.47059778},
{"learn":[0.385988078],"iteration":84,"passed_time":1.34211984,"remaining_time":14.44752534},
{"learn":[0.3857951642],"iteration":85,"passed_time":1.356956815,"remaining_time":14.4216108},
{"learn":[0.3854689242],"iteration":86,"passed_time":1.372089447,"remaining_time":14.39905362},
{"learn":[0.3852485557],"iteration":87,"passed_time":1.387464791,"remaining_time":14.37918057},
{"learn":[0.3850937848],"iteration":88,"passed_time":1.401588947,"remaining_time":14.34660147},
{"learn":[0.384871734],"iteration":89,"passed_time":1.415672509,"remaining_time":14.31402204},
{"learn":[0.3848226558],"iteration":90,"passed_time":1.427071991,"remaining_time":14.2550378},
{"learn":[0.3845906896],"iteration":91,"passed_time":1.442688707,"remaining_time":14.23871028},
{"learn":[0.3844127585],"iteration":92,"passed_time":1.456472361,"remaining_time":14.20452077},
{"learn":[0.3842637722],"iteration":93,"passed_time":1.468846748,"remaining_time":14.15718249},
{"learn":[0.3841808953],"iteration":94,"passed_time":1.480154398,"remaining_time":14.10041821},
{"learn":[0.3840020491],"iteration":95,"passed_time":1.493333767,"remaining_time":14.06222631},
{"learn":[0.3838571162],"iteration":96,"passed_time":1.507374268,"remaining_time":14.03256664},
{"learn":[0.3837357758],"iteration":97,"passed_time":1.522004794,"remaining_time":14.00865637},
{"learn":[0.3835073855],"iteration":98,"passed_time":1.537171015,"remaining_time":13.98980893},
{"learn":[0.3834053701],"iteration":99,"passed_time":1.549563804,"remaining_time":13.94607423},
{"learn":[0.3833039716],"iteration":100,"passed_time":1.561981218,"remaining_time":13.90317936},
{"learn":[0.3830723749],"iteration":101,"passed_time":1.577804068,"remaining_time":13.89086327},
{"learn":[0.3829890463],"iteration":102,"passed_time":1.593441568,"remaining_time":13.87686491},
{"learn":[0.3827644738],"iteration":103,"passed_time":1.606047374,"remaining_time":13.83671584},
{"learn":[0.3827028655],"iteration":104,"passed_time":1.624461479,"remaining_time":13.84660023},
{"learn":[0.3826334848],"iteration":105,"passed_time":1.637881526,"remaining_time":13.81383098},
{"learn":[0.3825772653],"iteration":106,"passed_time":1.660405361,"remaining_time":13.85740175},
{"learn":[0.3824498494],"iteration":107,"passed_time":1.669246564,"remaining_time":13.78674014},
{"learn":[0.3822994117],"iteration":108,"passed_time":1.678591642,"remaining_time":13.72133168},
{"learn":[0.3821269642],"iteration":109,"passed_time":1.693000084,"remaining_time":13.69790977},
{"learn":[0.3819557884],"iteration":110,"passed_time":1.702504875,"remaining_time":13.63537689},
{"learn":[0.3816533627],"iteration":111,"passed_time":1.713902345,"remaining_time":13.58879716},
{"learn":[0.3815713716],"iteration":112,"passed_time":1.726658885,"remaining_time":13.55350824},
{"learn":[0.3814447593],"iteration":113,"passed_time":1.740166034,"remaining_time":13.5244483},
{"learn":[0.3813866233],"iteration":114,"passed_time":1.750775106,"remaining_time":13.47335625},
{"learn":[0.3812017354],"iteration":115,"passed_time":1.76012361,"remaining_time":13.41335578},
{"learn":[0.3811310351],"iteration":116,"passed_time":1.770393676,"remaining_time":13.3611762},
{"learn":[0.3809459009],"iteration":117,"passed_time":1.781175216,"remaining_time":13.31353},
{"learn":[0.380794543],"iteration":118,"passed_time":1.79175299,"remaining_time":13.26499482},
{"learn":[0.3807477769],"iteration":119,"passed_time":1.802412646,"remaining_time":13.21769274},
{"learn":[0.3805928499],"iteration":120,"passed_time":1.814048107,"remaining_time":13.17808501},
{"learn":[0.3804269607],"iteration":121,"passed_time":1.827765707,"remaining_time":13.15392042},
{"learn":[0.3803575122],"iteration":122,"passed_time":1.841901495,"remaining_time":13.13290741},
{"learn":[0.3803254523],"iteration":123,"passed_time":1.85359465,"remaining_time":13.0947493},
{"learn":[0.3802722704],"iteration":124,"passed_time":1.86518574,"remaining_time":13.05630018},
{"learn":[0.3800905006],"iteration":125,"passed_time":1.874832188,"remaining_time":13.00478835},
{"learn":[0.3799069393],"iteration":126,"passed_time":1.885429512,"remaining_time":12.96047216},
{"learn":[0.3798406235],"iteration":127,"passed_time":1.896316128,"remaining_time":12.91865362},
{"learn":[0.379746197],"iteration":128,"passed_time":1.908323387,"remaining_time":12.88488116},
{"learn":[0.3796513106],"iteration":129,"passed_time":1.920548586,"remaining_time":12.85290208},
{"learn":[0.3794863598],"iteration":130,"passed_time":1.932811621,"remaining_time":12.82147556},
{"learn":[0.3792655643],"iteration":131,"passed_time":1.9431507,"remaining_time":12.77768794},
{"learn":[0.3791065647],"iteration":132,"passed_time":1.956122922,"remaining_time":12.75156822},
{"learn":[0.3787625458],"iteration":133,"passed_time":1.972905941,"remaining_time":12.75027272},
{"learn":[0.3786173349],"iteration":134,"passed_time":1.986770049,"remaining_time":12.73004513},
{"learn":[0.3782675322],"iteration":135,"passed_time":2.030508591,"remaining_time":12.89970164},
{"learn":[0.3780698126],"iteration":136,"passed_time":2.045450566,"remaining_time":12.88484554},
{"learn":[0.3780023473],"iteration":137,"passed_time":2.062435688,"remaining_time":12.88275045},
{"learn":[0.3779262013],"iteration":138,"passed_time":2.084167346,"remaining_time":12.90984234},
{"learn":[0.3777706025],"iteration":139,"passed_time":2.111485857,"remaining_time":12.97055598},
{"learn":[0.3776778676],"iteration":140,"passed_time":2.126935626,"remaining_time":12.9577142},
{"learn":[0.3775184619],"iteration":141,"passed_time":2.139936472,"remaining_time":12.93003868},
{"learn":[0.3774760874],"iteration":142,"passed_time":2.15195436,"remaining_time":12.89667753},
{"learn":[0.377420914],"iteration":143,"passed_time":2.165229426,"remaining_time":12.87108603},
{"learn":[0.3773410204],"iteration":144,"passed_time":2.18043752,"remaining_time":12.85706262},
{"learn":[0.3772668866],"iteration":145,"passed_time":2.195158817,"remaining_time":12.84017554},
{"learn":[0.3771150383],"iteration":146,"passed_time":2.207289239,"remaining_time":12.80828381},
{"learn":[0.3769887089],"iteration":147,"passed_time":2.220558696,"remaining_time":12.78321628},
{"learn":[0.3768217696],"iteration":148,"passed_time":2.23461187,"remaining_time":12.76278323},
{"learn":[0.3767613645],"iteration":149,"passed_time":2.249880631,"remaining_time":12.74932357},
{"learn":[0.3766815065],"iteration":150,"passed_time":2.265331861,"remaining_time":12.73686589},
{"learn":[0.3766367643],"iteration":151,"passed_time":2.278856037,"remaining_time":12.71361789},
{"learn":[0.3765828001],"iteration":152,"passed_time":2.292677187,"remaining_time":12.69214103},
{"learn":[0.3764572161],"iteration":153,"passed_time":2.309234193,"remaining_time":12.68579303},
{"learn":[0.37637687],"iteration":154,"passed_time":2.324269934,"remaining_time":12.67101996},
{"learn":[0.3762356398],"iteration":155,"passed_time":2.338673747,"remaining_time":12.65282463},
{"learn":[0.3761605286],"iteration":156,"passed_time":2.354662558,"remaining_time":12.64318813},
{"learn":[0.3760293062],"iteration":157,"passed_time":2.367094328,"remaining_time":12.61451534},
{"learn":[0.3759793493],"iteration":158,"passed_time":2.38202374,"remaining_time":12.59925764},
{"learn":[0.3759607522],"iteration":159,"passed_time":2.393844406,"remaining_time":12.56768313},
{"learn":[0.375901033],"iteration":160,"passed_time":2.407471988,"remaining_time":12.54577018},
{"learn":[0.375886978],"iteration":161,"passed_time":2.419770102,"remaining_time":12.51708238},
{"learn":[0.3756754754],"iteration":162,"passed_time":2.435834489,"remaining_time":12.50793538},
{"learn":[0.3756226188],"iteration":163,"passed_time":2.453161561,"remaining_time":12.50514064},
{"learn":[0.3755100581],"iteration":164,"passed_time":2.469638068,"remaining_time":12.49786537},
{"learn":[0.3754330552],"iteration":165,"passed_time":2.487801067,"remaining_time":12.49895235},
{"learn":[0.3753492985],"iteration":166,"passed_time":2.502121511,"remaining_time":12.48064203},
{"learn":[0.3753160722],"iteration":167,"passed_time":2.515332233,"remaining_time":12.45688344},
{"learn":[0.3751873138],"iteration":168,"passed_time":2.528761218,"remaining_time":12.43432291},
{"learn":[0.3751668141],"iteration":169,"passed_time":2.543218371,"remaining_time":12.4168897},
{"learn":[0.3750743992],"iteration":170,"passed_time":2.556850026,"remaining_time":12.39548931},
{"learn":[0.37493901],"iteration":171,"passed_time":2.5712627,"remaining_time":12.37793904},
{"learn":[0.3748204336],"iteration":172,"passed_time":2.585395655,"remaining_time":12.3590879},
{"learn":[0.3745669133],"iteration":173,"passed_time":2.599164945,"remaining_time":12.33856462},
{"learn":[0.3744865605],"iteration":174,"passed_time":2.61244594,"remaining_time":12.31581657},
{"learn":[0.3744632716],"iteration":175,"passed_time":2.625388721,"remaining_time":12.29159265},
{"learn":[0.3744081867],"iteration":176,"passed_time":2.638495942,"remaining_time":12.26826079},
{"learn":[0.3743973604],"iteration":177,"passed_time":2.648667462,"remaining_time":12.23148682},
{"learn":[0.3743503389],"iteration":178,"passed_time":2.662354282,"remaining_time":12.21113333},
{"learn":[0.3742380259],"iteration":179,"passed_time":2.676449158,"remaining_time":12.19271283},
{"learn":[0.3741237623],"iteration":180,"passed_time":2.690531819,"remaining_time":12.17428486},
{"learn":[0.3738514096],"iteration":181,"passed_time":2.704178241,"remaining_time":12.15394396},
{"learn":[0.3736960442],"iteration":182,"passed_time":2.715277105,"remaining_time":12.1223027},
{"learn":[0.3736734835],"iteration":183,"passed_time":2.726049368,"remaining_time":12.08943633},
{"learn":[0.3735803974],"iteration":184,"passed_time":2.737210106,"remaining_time":12.0585202},
{"learn":[0.3735227192],"iteration":185,"passed_time":2.751407761,"remaining_time":12.04110709},
{"learn":[0.3734585293],"iteration":186,"passed_time":2.765292389,"remaining_time":12.02236745},
{"learn":[0.373383346],"iteration":187,"passed_time":2.779060126,"remaining_time":12.00317459},
{"learn":[0.3733412737],"iteration":188,"passed_time":2.793186041,"remaining_time":11.98557608},
{"learn":[0.3733033949],"iteration":189,"passed_time":2.807852265,"remaining_time":11.97031755},
{"learn":[0.3732702192],"iteration":190,"passed_time":2.823933404,"remaining_time":11.96105824},
{"learn":[0.3732176144],"iteration":191,"passed_time":2.837280631,"remaining_time":11.94022266},
{"learn":[0.3731521673],"iteration":192,"passed_time":2.852964016,"remaining_time":11.92923296},
{"learn":[0.3730871775],"iteration":193,"passed_time":2.867529697,"remaining_time":11.91355121},
{"learn":[0.3730229461],"iteration":194,"passed_time":2.88350127,"remaining_time":11.90368473},
{"learn":[0.3729571304],"iteration":195,"passed_time":2.899336468,"remaining_time":11.89319653},
{"learn":[0.3729126523],"iteration":196,"passed_time":2.913554865,"remaining_time":11.87606374},
{"learn":[0.3728612914],"iteration":197,"passed_time":2.930233553,"remaining_time":11.86892581},
{"learn":[0.3728106867],"iteration":198,"passed_time":2.946804548,"remaining_time":11.86125851},
{"learn":[0.372737272],"iteration":199,"passed_time":2.957630207,"remaining_time":11.83052083},
{"learn":[0.3727027617],"iteration":200,"passed_time":2.97313401,"remaining_time":11.81857748},
{"learn":[0.3726238675],"iteration":201,"passed_time":2.985150189,"remaining_time":11.79282105},
{"learn":[0.3725932899],"iteration":202,"passed_time":2.999561498,"remaining_time":11.77660351},
{"learn":[0.372539585],"iteration":203,"passed_time":3.016573247,"remaining_time":11.77055051},
{"learn":[0.3725103883],"iteration":204,"passed_time":3.032315988,"remaining_time":11.75946932},
{"learn":[0.3724723832],"iteration":205,"passed_time":3.047965301,"remaining_time":11.74798276},
{"learn":[0.3724208863],"iteration":206,"passed_time":3.063484992,"remaining_time":11.73595942},
{"learn":[0.3724021832],"iteration":207,"passed_time":3.077630927,"remaining_time":11.71867161},
{"learn":[0.372359198],"iteration":208,"passed_time":3.091569604,"remaining_time":11.70062946},
{"learn":[0.3723222735],"iteration":209,"passed_time":3.104875286,"remaining_time":11.68024512},
{"learn":[0.3723027197],"iteration":210,"passed_time":3.12056058,"remaining_time":11.66882606},
{"learn":[0.3722595464],"iteration":211,"passed_time":3.136202255,"remaining_time":11.65720461},
{"learn":[0.3721397488],"iteration":212,"passed_time":3.152518574,"remaining_time":11.64803811},
{"learn":[0.3721151535],"iteration":213,"passed_time":3.167465818,"remaining_time":11.63377632},
{"learn":[0.3720115804],"iteration":214,"passed_time":3.179921046,"remaining_time":11.6104094},
{"learn":[0.3718018419],"iteration":215,"passed_time":3.197011061,"remaining_time":11.60396607},
{"learn":[0.3717220185],"iteration":216,"passed_time":3.212169469,"remaining_time":11.59045481},
{"learn":[0.3716225507],"iteration":217,"passed_time":3.225863561,"remaining_time":11.57167571},
{"learn":[0.3716074089],"iteration":218,"passed_time":3.239872863,"remaining_time":11.55406715},
{"learn":[0.3715706614],"iteration":219,"passed_time":3.255602927,"remaining_time":11.5425922},
{"learn":[0.3715454689],"iteration":220,"passed_time":3.269888779,"remaining_time":11.52598805},
{"learn":[0.3713868651],"iteration":221,"passed_time":3.284507044,"remaining_time":11.51056973},
{"learn":[0.371355875],"iteration":222,"passed_time":3.300152345,"remaining_time":11.49873709},
{"learn":[0.3713347258],"iteration":223,"passed_time":3.315586699,"remaining_time":11.48613964},
{"learn":[0.3712475755],"iteration":224,"passed_time":3.329687891,"remaining_time":11.46892496},
{"learn":[0.37121502],"iteration":225,"passed_time":3.343477015,"remaining_time":11.45066907},
{"learn":[0.3711244299],"iteration":226,"passed_time":3.358588526,"remaining_time":11.43695564},
{"learn":[0.3710932054],"iteration":227,"passed_time":3.374508789,"remaining_time":11.42596836},
{"learn":[0.3710536911],"iteration":228,"passed_time":3.388571755,"remaining_time":11.40868482},
{"learn":[0.3709596225],"iteration":229,"passed_time":3.405419544,"remaining_time":11.40075239},
{"learn":[0.3707928549],"iteration":230,"passed_time":3.421353396,"remaining_time":11.38970027},
{"learn":[0.3707777714],"iteration":231,"passed_time":3.437626024,"remaining_time":11.37972753},
{"learn":[0.3707240407],"iteration":232,"passed_time":3.452326643,"remaining_time":11.3645259},
{"learn":[0.3706959034],"iteration":233,"passed_time":3.46856238,"remaining_time":11.35435377},
{"learn":[0.3705259063],"iteration":234,"passed_time":3.484857933,"remaining_time":11.34432476},
{"learn":[0.3704874481],"iteration":235,"passed_time":3.497881276,"remaining_time":11.32364956},
{"learn":[0.3704249473],"iteration":236,"passed_time":3.514322053,"remaining_time":11.31404104},
{"learn":[0.3703839943],"iteration":237,"passed_time":3.530329232,"remaining_time":11.30298687},
{"learn":[0.370255558],"iteration":238,"passed_time":3.544546977,"remaining_time":11.28619351},
{"learn":[0.3702236599],"iteration":239,"passed_time":3.56117646,"remaining_time":11.27705879},
{"learn":[0.3701409368],"iteration":240,"passed_time":3.576225165,"remaining_time":11.2628834},
{"learn":[0.3701087303],"iteration":241,"passed_time":3.59462278,"remaining_time":11.25919036},
{"learn":[0.3700608705],"iteration":242,"passed_time":3.610479557,"remaining_time":11.24746101},
{"learn":[0.369997791],"iteration":243,"passed_time":3.626333924,"remaining_time":11.23569035},
{"learn":[0.3699303469],"iteration":244,"passed_time":3.644107673,"remaining_time":11.2298012},
{"learn":[0.3699070059],"iteration":245,"passed_time":3.65901739,"remaining_time":11.21503704},
{"learn":[0.3698519257],"iteration":246,"passed_time":3.675274376,"remaining_time":11.20437897},
{"learn":[0.3698307127],"iteration":247,"passed_time":3.689148301,"remaining_time":11.18644969},
{"learn":[0.3697137335],"iteration":248,"passed_time":3.704009643,"remaining_time":11.17153109},
{"learn":[0.3696954434],"iteration":249,"passed_time":3.718286738,"remaining_time":11.15486021},
{"learn":[0.3696535576],"iteration":250,"passed_time":3.732993138,"remaining_time":11.13948948},
{"learn":[0.3696190525],"iteration":251,"passed_time":3.744951185,"remaining_time":11.11596622},
{"learn":[0.3695408347],"iteration":252,"passed_time":3.760207679,"remaining_time":11.10227327},
{"learn":[0.3695229919],"iteration":253,"passed_time":3.776062599,"remaining_time":11.09032559},
{"learn":[0.3695045669],"iteration":254,"passed_time":3.789206957,"remaining_time":11.07042817},
{"learn":[0.3692196776],"iteration":255,"passed_time":3.804545612,"remaining_time":11.05696068},
{"learn":[0.3691696728],"iteration":256,"passed_time":3.81943846,"remaining_time":11.04218979},
{"learn":[0.3691263056],"iteration":257,"passed_time":3.835747446,"remaining_time":11.03149072},
{"learn":[0.369038899],"iteration":258,"passed_time":3.851226417,"remaining_time":11.01837365},
{"learn":[0.3690215755],"iteration":259,"passed_time":3.863209018,"remaining_time":10.9952872},
{"learn":[0.3689101238],"iteration":260,"passed_time":3.87389692,"remaining_time":10.96862002},
{"learn":[0.3688293013],"iteration":261,"passed_time":3.885433882,"remaining_time":10.94446643},
{"learn":[0.3687671989],"iteration":262,"passed_time":3.898724281,"remaining_time":10.92532241},
{"learn":[0.3687408519],"iteration":263,"passed_time":3.911988758,"remaining_time":10.90615048},
{"learn":[0.3687095373],"iteration":264,"passed_time":3.925491236,"remaining_time":10.88768324},
{"learn":[0.3686159276],"iteration":265,"passed_time":3.937604481,"remaining_time":10.86541988},
{"learn":[0.3684429581],"iteration":266,"passed_time":3.951256125,"remaining_time":10.84745595},
{"learn":[0.3684009414],"iteration":267,"passed_time":3.964403261,"remaining_time":10.82814622},
{"learn":[0.3682354208],"iteration":268,"passed_time":3.976831294,"remaining_time":10.80692816},
{"learn":[0.3680095228],"iteration":269,"passed_time":3.98827909,"remaining_time":10.78312495},
{"learn":[0.3679744023],"iteration":270,"passed_time":4.001071346,"remaining_time":10.76302956},
{"learn":[0.3679557174],"iteration":271,"passed_time":4.014442097,"remaining_time":10.7445362},
{"learn":[0.3678963767],"iteration":272,"passed_time":4.027487597,"remaining_time":10.72521422},
{"learn":[0.3678730896],"iteration":273,"passed_time":4.041185865,"remaining_time":10.70766766},
{"learn":[0.3678420307],"iteration":274,"passed_time":4.052129452,"remaining_time":10.68288674},
{"learn":[0.3677609371],"iteration":275,"passed_time":4.065299192,"remaining_time":10.66404571},
{"learn":[0.3676326801],"iteration":276,"passed_time":4.07913705,"remaining_time":10.64698948},
{"learn":[0.367600282],"iteration":277,"passed_time":4.091708303,"remaining_time":10.62666689},
{"learn":[0.367564362],"iteration":278,"passed_time":4.102746946,"remaining_time":10.60243924},
{"learn":[0.367444366],"iteration":279,"passed_time":4.116755299,"remaining_time":10.5859422},
{"learn":[0.3673921426],"iteration":280,"passed_time":4.129253036,"remaining_time":10.56559763},
{"learn":[0.3673768539],"iteration":281,"passed_time":4.141830652,"remaining_time":10.54551209},
{"learn":[0.3673275291],"iteration":282,"passed_time":4.153796187,"remaining_time":10.52392886},
{"learn":[0.3672655853],"iteration":283,"passed_time":4.167098536,"remaining_time":10.50578363},
{"learn":[0.3672236887],"iteration":284,"passed_time":4.182153391,"remaining_time":10.49206903},
{"learn":[0.3671725015],"iteration":285,"passed_time":4.19528759,"remaining_time":10.47355014},
{"learn":[0.3671164978],"iteration":286,"passed_time":4.208566641,"remaining_time":10.45542862},
{"learn":[0.3670740072],"iteration":287,"passed_time":4.22461829,"remaining_time":10.44419522},
{"learn":[0.3670251236],"iteration":288,"passed_time":4.238988171,"remaining_time":10.42879097},
{"learn":[0.3670085282],"iteration":289,"passed_time":4.254283457,"remaining_time":10.4156595},
{"learn":[0.366955779],"iteration":290,"passed_time":4.266651503,"remaining_time":10.39538115},
{"learn":[0.3668139239],"iteration":291,"passed_time":4.280784097,"remaining_time":10.37943541},
{"learn":[0.36672389],"iteration":292,"passed_time":4.295669486,"remaining_time":10.36531852},
{"learn":[0.3666286676],"iteration":293,"passed_time":4.316835104,"remaining_time":10.36627749},
{"learn":[0.3666156979],"iteration":294,"passed_time":4.331447126,"remaining_time":10.35142449},
{"learn":[0.3665828727],"iteration":295,"passed_time":4.34590034,"remaining_time":10.3361954},
{"learn":[0.3664454183],"iteration":296,"passed_time":4.361840095,"remaining_time":10.32449019},
{"learn":[0.3664021253],"iteration":297,"passed_time":4.377023069,"remaining_time":10.31097381},
{"learn":[0.3663548325],"iteration":298,"passed_time":4.390930165,"remaining_time":10.294455},
{"learn":[0.3663117642],"iteration":299,"passed_time":4.406584177,"remaining_time":10.28202975},
{"learn":[0.3662890392],"iteration":300,"passed_time":4.422628623,"remaining_time":10.27048973},
{"learn":[0.366251356],"iteration":301,"passed_time":4.43695929,"remaining_time":10.25495889},
{"learn":[0.3660418867],"iteration":302,"passed_time":4.451060038,"remaining_time":10.23890708},
{"learn":[0.3660071737],"iteration":303,"passed_time":4.465761658,"remaining_time":10.2242438},
{"learn":[0.3659106492],"iteration":304,"passed_time":4.480785515,"remaining_time":10.21031453},
{"learn":[0.3658781183],"iteration":305,"passed_time":4.494143597,"remaining_time":10.19260018},
{"learn":[0.3658694284],"iteration":306,"passed_time":4.508799692,"remaining_time":10.17784426},
{"learn":[0.3657923698],"iteration":307,"passed_time":4.524532154,"remaining_time":10.16550731},
{"learn":[0.3657670343],"iteration":308,"passed_time":4.538872483,"remaining_time":10.15003523},
{"learn":[0.3657370064],"iteration":309,"passed_time":4.552330654,"remaining_time":10.13260694},
{"learn":[0.3657045953],"iteration":310,"passed_time":4.567382026,"remaining_time":10.11873381},
{"learn":[0.365681898],"iteration":311,"passed_time":4.581420501,"remaining_time":10.10261957},
{"learn":[0.3656383598],"iteration":312,"passed_time":4.594289642,"remaining_time":10.08395203},
{"learn":[0.3656239985],"iteration":313,"passed_time":4.608430173,"remaining_time":10.06809904},
{"learn":[0.365450785],"iteration":314,"passed_time":4.622741916,"remaining_time":10.05262925},
{"learn":[0.3652433859],"iteration":315,"passed_time":4.646107831,"remaining_time":10.05676505},
{"learn":[0.3652059869],"iteration":316,"passed_time":4.665554725,"remaining_time":10.05228352},
{"learn":[0.3651565718],"iteration":317,"passed_time":4.681656779,"remaining_time":10.04053435},
{"learn":[0.3650660912],"iteration":318,"passed_time":4.70394922,"remaining_time":10.0419731},
{"learn":[0.3650337427],"iteration":319,"passed_time":4.720055611,"remaining_time":10.03011817},
{"learn":[0.364747532],"iteration":320,"passed_time":4.734601539,"remaining_time":10.01493596},
{"learn":[0.3646084672],"iteration":321,"passed_time":4.751055224,"remaining_time":10.00377466},
{"learn":[0.3645679447],"iteration":322,"passed_time":4.769908167,"remaining_time":9.997609377},
{"learn":[0.3644984135],"iteration":323,"passed_time":4.785815257,"remaining_time":9.985219487},
{"learn":[0.3644562501],"iteration":324,"passed_time":4.801227888,"remaining_time":9.971780997},
{"learn":[0.3644300081],"iteration":325,"passed_time":4.81606226,"remaining_time":9.957134856},
{"learn":[0.3643675294],"iteration":326,"passed_time":4.833447618,"remaining_time":9.947737758},
{"learn":[0.3643474908],"iteration":327,"passed_time":4.847346311,"remaining_time":9.93114854},
{"learn":[0.3643340986],"iteration":328,"passed_time":4.860679183,"remaining_time":9.913421677},
{"learn":[0.364150223],"iteration":329,"passed_time":4.875586876,"remaining_time":9.898918809},
{"learn":[0.3641202246],"iteration":330,"passed_time":4.890625112,"remaining_time":9.884677342},
{"learn":[0.3639369218],"iteration":331,"passed_time":4.906687056,"remaining_time":9.872490824},
{"learn":[0.3638757906],"iteration":332,"passed_time":4.920069093,"remaining_time":9.854913168},
{"learn":[0.3638374202],"iteration":333,"passed_time":4.933489798,"remaining_time":9.837437741},
{"learn":[0.3638282071],"iteration":334,"passed_time":4.94700827,"remaining_time":9.820180596},
{"learn":[0.3638084581],"iteration":335,"passed_time":4.963661162,"remaining_time":9.809139915},
{"learn":[0.3637281482],"iteration":336,"passed_time":4.979085593,"remaining_time":9.795649104},
{"learn":[0.3636436397],"iteration":337,"passed_time":4.994319555,"remaining_time":9.781773803},
{"learn":[0.3636178445],"iteration":338,"passed_time":5.012366508,"remaining_time":9.773375404},
{"learn":[0.3635656835],"iteration":339,"passed_time":5.029646585,"remaining_time":9.763431606},
{"learn":[0.3634872189],"iteration":340,"passed_time":5.044379137,"remaining_time":9.748521557},
{"learn":[0.3634492363],"iteration":341,"passed_time":5.058929575,"remaining_time":9.733262164},
{"learn":[0.3633466021],"iteration":342,"passed_time":5.07559701,"remaining_time":9.72206191},
{"learn":[0.3632452967],"iteration":343,"passed_time":5.089273103,"remaining_time":9.705125453},
{"learn":[0.3630806703],"iteration":344,"passed_time":5.104995838,"remaining_time":9.692093547},
{"learn":[0.3629186093],"iteration":345,"passed_time":5.121784882,"remaining_time":9.681061598},
{"learn":[0.3628898804],"iteration":346,"passed_time":5.137586901,"remaining_time":9.668139038},
{"learn":[0.3627805308],"iteration":347,"passed_time":5.153455482,"remaining_time":9.655324639},
{"learn":[0.3627454704],"iteration":348,"passed_time":5.169748096,"remaining_time":9.643283698},
{"learn":[0.3627092445],"iteration":349,"passed_time":5.185667802,"remaining_time":9.630525917},
{"learn":[0.362649829],"iteration":350,"passed_time":5.200805582,"remaining_time":9.616304338},
{"learn":[0.3626172378],"iteration":351,"passed_time":5.215957233,"remaining_time":9.602103088},
{"learn":[0.3625798544],"iteration":352,"passed_time":5.229609248,"remaining_time":9.585147828},
{"learn":[0.362551205],"iteration":353,"passed_time":5.242364972,"remaining_time":9.566575627},
{"learn":[0.3624583906],"iteration":354,"passed_time":5.256144859,"remaining_time":9.549896997},
{"learn":[0.3624249986],"iteration":355,"passed_time":5.269908559,"remaining_time":9.533205371},
{"learn":[0.3623941634],"iteration":356,"passed_time":5.282259016,"remaining_time":9.513984726},
{"learn":[0.3621724905],"iteration":357,"passed_time":5.301118851,"remaining_time":9.506475705},
{"learn":[0.3621430147],"iteration":358,"passed_time":5.317797841,"remaining_time":9.495009515},
{"learn":[0.3620684507],"iteration":359,"passed_time":5.332706257,"remaining_time":9.480366679},
{"learn":[0.3620272816],"iteration":360,"passed_time":5.34917736,"remaining_time":9.468488457},
{"learn":[0.3619923369],"iteration":361,"passed_time":5.364048555,"remaining_time":9.453765133},
{"learn":[0.3619339581],"iteration":362,"passed_time":5.379334418,"remaining_time":9.439768662},
{"learn":[0.361909536],"iteration":363,"passed_time":5.394510183,"remaining_time":9.425572737},
{"learn":[0.361891255],"iteration":364,"passed_time":5.408225659,"remaining_time":9.408830942},
{"learn":[0.3618714981],"iteration":365,"passed_time":5.423197814,"remaining_time":9.394282552},
{"learn":[0.3618056229],"iteration":366,"passed_time":5.437393193,"remaining_time":9.378392075},
{"learn":[0.3617834914],"iteration":367,"passed_time":5.451403604,"remaining_time":9.362193147},
{"learn":[0.3617389329],"iteration":368,"passed_time":5.467731372,"remaining_time":9.349968824},
{"learn":[0.3616777622],"iteration":369,"passed_time":5.482996096,"remaining_time":9.335912272},
{"learn":[0.3615854167],"iteration":370,"passed_time":5.498250583,"remaining_time":9.321831851},
{"learn":[0.3615596365],"iteration":371,"passed_time":5.513306872,"remaining_time":9.307410526},
{"learn":[0.3614843846],"iteration":372,"passed_time":5.527205925,"remaining_time":9.291040522},
{"learn":[0.3614564423],"iteration":373,"passed_time":5.540971987,"remaining_time":9.274461134},
{"learn":[0.3614296924],"iteration":374,"passed_time":5.555983835,"remaining_time":9.259973058},
{"learn":[0.3613738592],"iteration":375,"passed_time":5.573117615,"remaining_time":9.249003702},
{"learn":[0.3613460792],"iteration":376,"passed_time":5.588135338,"remaining_time":9.234504817},
{"learn":[0.3613268497],"iteration":377,"passed_time":5.602206729,"remaining_time":9.218445994},
{"learn":[0.361301036],"iteration":378,"passed_time":5.614767687,"remaining_time":9.199922779},
{"learn":[0.3612495414],"iteration":379,"passed_time":5.632361158,"remaining_time":9.18964189},
{"learn":[0.3611896967],"iteration":380,"passed_time":5.64494548,"remaining_time":9.171184388},
{"learn":[0.3611599858],"iteration":381,"passed_time":5.659752012,"remaining_time":9.156352731},
{"learn":[0.3611191258],"iteration":382,"passed_time":5.675271335,"remaining_time":9.142669488},
{"learn":[0.3610709792],"iteration":383,"passed_time":5.692209606,"remaining_time":9.13125291},
{"learn":[0.3609587254],"iteration":384,"passed_time":5.70730685,"remaining_time":9.116866786},
{"learn":[0.3608614682],"iteration":385,"passed_time":5.723133957,"remaining_time":9.103637952},
{"learn":[0.3608371281],"iteration":386,"passed_time":5.737232306,"remaining_time":9.087657374},
{"learn":[0.3607840551],"iteration":387,"passed_time":5.752617096,"remaining_time":9.073715625},
{"learn":[0.3607033922],"iteration":388,"passed_time":5.768294095,"remaining_time":9.060225429},
{"learn":[0.3606181303],"iteration":389,"passed_time":5.784214958,"remaining_time":9.047105448},
{"learn":[0.3605750398],"iteration":390,"passed_time":5.799765969,"remaining_time":9.033395077},
{"learn":[0.3605606255],"iteration":391,"passed_time":5.814710433,"remaining_time":9.018734549},
{"learn":[0.3605549692],"iteration":392,"passed_time":5.830575364,"remaining_time":9.005494264},
{"learn":[0.3605479627],"iteration":393,"passed_time":5.845163272,"remaining_time":8.990276504},
{"learn":[0.3604083181],"iteration":394,"passed_time":5.859318861,"remaining_time":8.974399774},
{"learn":[0.3603832563],"iteration":395,"passed_time":5.87443432,"remaining_time":8.959995782},
{"learn":[0.3603579419],"iteration":396,"passed_time":5.889213108,"remaining_time":8.945076837},
{"learn":[0.360336772],"iteration":397,"passed_time":5.900390354,"remaining_time":8.924711038},
{"learn":[0.3603139998],"iteration":398,"passed_time":5.915537335,"remaining_time":8.910370773},
{"learn":[0.3601972251],"iteration":399,"passed_time":5.929527059,"remaining_time":8.894290588},
{"learn":[0.3601645434],"iteration":400,"passed_time":5.94402197,"remaining_time":8.878975462},
{"learn":[0.3601582998],"iteration":401,"passed_time":5.955834561,"remaining_time":8.859674297},
{"learn":[0.3601479935],"iteration":402,"passed_time":5.969590248,"remaining_time":8.84328878},
{"learn":[0.3600397371],"iteration":403,"passed_time":5.982684745,"remaining_time":8.825940862},
{"learn":[0.3600253589],"iteration":404,"passed_time":5.99689481,"remaining_time":8.810252869},
{"learn":[0.3599741883],"iteration":405,"passed_time":6.009179671,"remaining_time":8.791755479},
{"learn":[0.3599379732],"iteration":406,"passed_time":6.023237941,"remaining_time":8.775872479},
{"learn":[0.35988315],"iteration":407,"passed_time":6.035744842,"remaining_time":8.757747418},
{"learn":[0.3598357605],"iteration":408,"passed_time":6.049536537,"remaining_time":8.74150634},
{"learn":[0.3598066749],"iteration":409,"passed_time":6.063548937,"remaining_time":8.725594811},
{"learn":[0.3597402476],"iteration":410,"passed_time":6.075875943,"remaining_time":8.707277204},
{"learn":[0.3597021602],"iteration":411,"passed_time":6.087048231,"remaining_time":8.687340679},
{"learn":[0.3596559362],"iteration":412,"passed_time":6.099519948,"remaining_time":8.669293485},
{"learn":[0.3596371103],"iteration":413,"passed_time":6.112829137,"remaining_time":8.652458633},
{"learn":[0.3596153573],"iteration":414,"passed_time":6.125399746,"remaining_time":8.634599642},
{"learn":[0.3595503056],"iteration":415,"passed_time":6.14166792,"remaining_time":8.621956888},
{"learn":[0.3595027281],"iteration":416,"passed_time":6.155676132,"remaining_time":8.606137134},
{"learn":[0.3594223167],"iteration":417,"passed_time":6.168930873,"remaining_time":8.589276957},
{"learn":[0.3593521896],"iteration":418,"passed_time":6.182277744,"remaining_time":8.57256174},
{"learn":[0.359338488],"iteration":419,"passed_time":6.196198107,"remaining_time":8.556654529},
{"learn":[0.3593000263],"iteration":420,"passed_time":6.21009728,"remaining_time":8.540727613},
{"learn":[0.3592333617],"iteration":421,"passed_time":6.223070882,"remaining_time":8.523542583},
{"learn":[0.3592042255],"iteration":422,"passed_time":6.236776901,"remaining_time":8.507376529},
{"learn":[0.3591865068],"iteration":423,"passed_time":6.250484789,"remaining_time":8.491224619},
{"learn":[0.3591514074],"iteration":424,"passed_time":6.265299229,"remaining_time":8.47658131},
{"learn":[0.3591204616],"iteration":425,"passed_time":6.279151369,"remaining_time":8.460640577},
{"learn":[0.3590804237],"iteration":426,"passed_time":6.295123081,"remaining_time":8.447553924},
{"learn":[0.3590735143],"iteration":427,"passed_time":6.30870556,"remaining_time":8.431260701},
{"learn":[0.3590310422],"iteration":428,"passed_time":6.325570377,"remaining_time":8.419348917},
{"learn":[0.3590247781],"iteration":429,"passed_time":6.342653137,"remaining_time":8.407702995},
{"learn":[0.3589714164],"iteration":430,"passed_time":6.357066298,"remaining_time":8.392507479},
{"learn":[0.3589364601],"iteration":431,"passed_time":6.368820475,"remaining_time":8.373819514},
{"learn":[0.3589055658],"iteration":432,"passed_time":6.383938006,"remaining_time":8.359567782},
{"learn":[0.3588544044],"iteration":433,"passed_time":6.399493677,"remaining_time":8.345883459},
{"learn":[0.3588148092],"iteration":434,"passed_time":6.414296206,"remaining_time":8.331212314},
{"learn":[0.3588019667],"iteration":435,"passed_time":6.426516161,"remaining_time":8.313199804},
{"learn":[0.3587748574],"iteration":436,"passed_time":6.440922278,"remaining_time":8.298030303},
{"learn":[0.3587248241],"iteration":437,"passed_time":6.458498563,"remaining_time":8.286931946},
{"learn":[0.3586821803],"iteration":438,"passed_time":6.476466881,"remaining_time":8.276305057},
{"learn":[0.3586456982],"iteration":439,"passed_time":6.493739471,"remaining_time":8.264759327},
{"learn":[0.3586276896],"iteration":440,"passed_time":6.509901812,"remaining_time":8.251780302},
{"learn":[0.3585377213],"iteration":441,"passed_time":6.524815655,"remaining_time":8.237210714},
{"learn":[0.3585067818],"iteration":442,"passed_time":6.539219404,"remaining_time":8.221998212},
{"learn":[0.3584670168],"iteration":443,"passed_time":6.552489524,"remaining_time":8.205369765},
{"learn":[0.3584339973],"iteration":444,"passed_time":6.565581541,"remaining_time":8.188534281},
{"learn":[0.3584247846],"iteration":445,"passed_time":6.577434383,"remaining_time":8.170176341},
{"learn":[0.3583922833],"iteration":446,"passed_time":6.591714349,"remaining_time":8.154850191},
{"learn":[0.3583526365],"iteration":447,"passed_time":6.603968818,"remaining_time":8.137033008},
{"learn":[0.3583333376],"iteration":448,"passed_time":6.621466388,"remaining_time":8.125674788},
{"learn":[0.3582885851],"iteration":449,"passed_time":6.635414175,"remaining_time":8.109950658},
{"learn":[0.3582535808],"iteration":450,"passed_time":6.649845336,"remaining_time":8.094822815},
{"learn":[0.3582235564],"iteration":451,"passed_time":6.661866469,"remaining_time":8.076776161},
{"learn":[0.3582052536],"iteration":452,"passed_time":6.673674286,"remaining_time":8.058498531},
{"learn":[0.3581966636],"iteration":453,"passed_time":6.683640407,"remaining_time":8.038034498},
{"learn":[0.358178172],"iteration":454,"passed_time":6.697081995,"remaining_time":8.021779532},
{"learn":[0.3581612479],"iteration":455,"passed_time":6.709225524,"remaining_time":8.003988345},
{"learn":[0.3581445893],"iteration":456,"passed_time":6.72232137,"remaining_time":7.9873534},
{"learn":[0.3581230787],"iteration":457,"passed_time":6.734815458,"remaining_time":7.970021787},
{"learn":[0.3580539031],"iteration":458,"passed_time":6.749064605,"remaining_time":7.954779851},
{"learn":[0.3580240764],"iteration":459,"passed_time":6.760309214,"remaining_time":7.936015164},
{"learn":[0.3579827252],"iteration":460,"passed_time":6.772726731,"remaining_time":7.918654464},
{"learn":[0.3579775031],"iteration":461,"passed_time":6.783551137,"remaining_time":7.899459982},
{"learn":[0.3579468611],"iteration":462,"passed_time":6.79777589,"remaining_time":7.884245471},
{"learn":[0.3579228006],"iteration":463,"passed_time":6.812214207,"remaining_time":7.869281929},
{"learn":[0.357870147],"iteration":464,"passed_time":6.825004555,"remaining_time":7.852424596},
{"learn":[0.3578541949],"iteration":465,"passed_time":6.837371109,"remaining_time":7.835099082},
{"learn":[0.3578214963],"iteration":466,"passed_time":6.85093467,"remaining_time":7.819160983},
{"learn":[0.3578046281],"iteration":467,"passed_time":6.862996643,"remaining_time":7.801526099},
{"learn":[0.3577771793],"iteration":468,"passed_time":6.874141686,"remaining_time":7.782876834},
{"learn":[0.3577597038],"iteration":469,"passed_time":6.884887922,"remaining_time":7.763809784},
{"learn":[0.3577274312],"iteration":470,"passed_time":6.900582015,"remaining_time":7.750335215},
{"learn":[0.357678886],"iteration":471,"passed_time":6.913442219,"remaining_time":7.733681126},
{"learn":[0.3576453802],"iteration":472,"passed_time":6.929531863,"remaining_time":7.720641208},
{"learn":[0.3576334108],"iteration":473,"passed_time":6.942794998,"remaining_time":7.704451834},
{"learn":[0.3576067213],"iteration":474,"passed_time":6.955508364,"remaining_time":7.68766714},
{"learn":[0.3575388808],"iteration":475,"passed_time":6.968695841,"remaining_time":7.671421472},
{"learn":[0.3575158084],"iteration":476,"passed_time":6.982223205,"remaining_time":7.655561292},
{"learn":[0.3574965046],"iteration":477,"passed_time":6.995719625,"remaining_time":7.63967708},
{"learn":[0.357467759],"iteration":478,"passed_time":7.009341806,"remaining_time":7.623939626},
{"learn":[0.3574405468],"iteration":479,"passed_time":7.024659545,"remaining_time":7.61004784},
{"learn":[0.3574183432],"iteration":480,"passed_time":7.036494083,"remaining_time":7.592391744},
{"learn":[0.3573861789],"iteration":481,"passed_time":7.050459923,"remaining_time":7.577050291},
{"learn":[0.3572813306],"iteration":482,"passed_time":7.067135701,"remaining_time":7.564615233},
{"learn":[0.3572410467],"iteration":483,"passed_time":7.084944735,"remaining_time":7.553370833},
{"learn":[0.357206802],"iteration":484,"passed_time":7.101963286,"remaining_time":7.541259985},
{"learn":[0.3571884776],"iteration":485,"passed_time":7.118225387,"remaining_time":7.528328908},
{"learn":[0.3571263688],"iteration":486,"passed_time":7.131272066,"remaining_time":7.511997064},
{"learn":[0.3571136429],"iteration":487,"passed_time":7.146893761,"remaining_time":7.498380339},
{"learn":[0.3570142922],"iteration":488,"passed_time":7.16328736,"remaining_time":7.485562047},
{"learn":[0.3569917434],"iteration":489,"passed_time":7.180706532,"remaining_time":7.473796594},
{"learn":[0.3569684317],"iteration":490,"passed_time":7.198964072,"remaining_time":7.462877215},
{"learn":[0.3569609696],"iteration":491,"passed_time":7.214182677,"remaining_time":7.448790243},
{"learn":[0.3569281024],"iteration":492,"passed_time":7.228693119,"remaining_time":7.433970408},
{"learn":[0.3569034818],"iteration":493,"passed_time":7.245554607,"remaining_time":7.421559982},
{"learn":[0.356867666],"iteration":494,"passed_time":7.263170437,"remaining_time":7.409901153},
{"learn":[0.3568542369],"iteration":495,"passed_time":7.278290666,"remaining_time":7.395682451},
{"learn":[0.356840283],"iteration":496,"passed_time":7.292190457,"remaining_time":7.38022495},
{"learn":[0.3567976794],"iteration":497,"passed_time":7.311065892,"remaining_time":7.369789313},
{"learn":[0.3567258286],"iteration":498,"passed_time":7.327006464,"remaining_time":7.356373224},
{"learn":[0.3566819288],"iteration":499,"passed_time":7.346050946,"remaining_time":7.346050946},
{"learn":[0.3566670691],"iteration":500,"passed_time":7.361922222,"remaining_time":7.332533311},
{"learn":[0.3566628191],"iteration":501,"passed_time":7.37667428,"remaining_time":7.317895999},
{"learn":[0.3566272993],"iteration":502,"passed_time":7.394027378,"remaining_time":7.305828244},
{"learn":[0.356597298],"iteration":503,"passed_time":7.412774424,"remaining_time":7.295111338},
{"learn":[0.3565471718],"iteration":504,"passed_time":7.42844478,"remaining_time":7.281346864},
{"learn":[0.3565403872],"iteration":505,"passed_time":7.443837138,"remaining_time":7.267303451},
{"learn":[0.3565188145],"iteration":506,"passed_time":7.459108225,"remaining_time":7.253136795},
{"learn":[0.3564978939],"iteration":507,"passed_time":7.473564546,"remaining_time":7.238176687},
{"learn":[0.3564901626],"iteration":508,"passed_time":7.486535504,"remaining_time":7.221785722},
{"learn":[0.3564839359],"iteration":509,"passed_time":7.501832906,"remaining_time":7.20764338},
{"learn":[0.3564514206],"iteration":510,"passed_time":7.517050893,"remaining_time":7.193420522},
{"learn":[0.3564086298],"iteration":511,"passed_time":7.530698912,"remaining_time":7.1776974},
{"learn":[0.3563894911],"iteration":512,"passed_time":7.546077912,"remaining_time":7.16362562},
{"learn":[0.3563509374],"iteration":513,"passed_time":7.56203224,"remaining_time":7.150092741},
{"learn":[0.3563437862],"iteration":514,"passed_time":7.574711882,"remaining_time":7.13346653},
{"learn":[0.3563330403],"iteration":515,"passed_time":7.588939021,"remaining_time":7.118307144},
{"learn":[0.356312596],"iteration":516,"passed_time":7.603597027,"remaining_time":7.103553895},
{"learn":[0.3562917247],"iteration":517,"passed_time":7.615993425,"remaining_time":7.086696585},
{"learn":[0.3562846578],"iteration":518,"passed_time":7.631314083,"remaining_time":7.072566617},
{"learn":[0.3562729448],"iteration":519,"passed_time":7.644970355,"remaining_time":7.056895712},
{"learn":[0.3562284954],"iteration":520,"passed_time":7.657468631,"remaining_time":7.040167897},
{"learn":[0.3562139543],"iteration":521,"passed_time":7.676542582,"remaining_time":7.02947769},
{"learn":[0.3561615145],"iteration":522,"passed_time":7.69078442,"remaining_time":7.014348314},
{"learn":[0.3561465063],"iteration":523,"passed_time":7.704550117,"remaining_time":6.998789801},
{"learn":[0.3561191234],"iteration":524,"passed_time":7.716390706,"remaining_time":6.981496353},
{"learn":[0.3560911367],"iteration":525,"passed_time":7.73154362,"remaining_time":6.967208509},
{"learn":[0.3560368096],"iteration":526,"passed_time":7.749599218,"remaining_time":6.955522638},
{"learn":[0.3560143946],"iteration":527,"passed_time":7.767118543,"remaining_time":6.943333243},
{"learn":[0.3559287292],"iteration":528,"passed_time":7.784766843,"remaining_time":6.931238531},
{"learn":[0.3559009897],"iteration":529,"passed_time":7.802097033,"remaining_time":6.918840765},
{"learn":[0.3558811201],"iteration":530,"passed_time":7.819338247,"remaining_time":6.906345834},
{"learn":[0.3558531679],"iteration":531,"passed_time":7.83705362,"remaining_time":6.894250177},
{"learn":[0.3558189024],"iteration":532,"passed_time":7.856878593,"remaining_time":6.883981806},
{"learn":[0.3557902875],"iteration":533,"passed_time":7.874576017,"remaining_time":6.871821019},
{"learn":[0.3557529747],"iteration":534,"passed_time":7.891116051,"remaining_time":6.858633577},
{"learn":[0.3557180784],"iteration":535,"passed_time":7.908887937,"remaining_time":6.846500006},
{"learn":[0.3557140914],"iteration":536,"passed_time":7.928765991,"remaining_time":6.836161366},
{"learn":[0.3557010922],"iteration":537,"passed_time":7.944467273,"remaining_time":6.822200521},
{"learn":[0.3556712785],"iteration":538,"passed_time":7.962227149,"remaining_time":6.809993907},
{"learn":[0.3556543741],"iteration":539,"passed_time":7.978797904,"remaining_time":6.79675377},
{"learn":[0.3556307474],"iteration":540,"passed_time":7.996392706,"remaining_time":6.784370152},
{"learn":[0.3555543547],"iteration":541,"passed_time":8.011151551,"remaining_time":6.769570868},
{"learn":[0.3555387105],"iteration":542,"passed_time":8.026492662,"remaining_time":6.75526178},
{"learn":[0.3555254777],"iteration":543,"passed_time":8.042470279,"remaining_time":6.74148244},
{"learn":[0.3555096322],"iteration":544,"passed_time":8.058079825,"remaining_time":6.727387744},
{"learn":[0.3554860569],"iteration":545,"passed_time":8.076970172,"remaining_time":6.716015491},
{"learn":[0.3554717762],"iteration":546,"passed_time":8.099943053,"remaining_time":6.707996715},
{"learn":[0.355456196],"iteration":547,"passed_time":8.123343595,"remaining_time":6.700276104},
{"learn":[0.3554436487],"iteration":548,"passed_time":8.139759621,"remaining_time":6.686760636},
{"learn":[0.3554213394],"iteration":549,"passed_time":8.158700709,"remaining_time":6.67530058},
{"learn":[0.3554149608],"iteration":550,"passed_time":8.173206962,"remaining_time":6.660199503},
{"learn":[0.355372356],"iteration":551,"passed_time":8.187961645,"remaining_time":6.645302205},
{"learn":[0.3553662124],"iteration":552,"passed_time":8.203534179,"remaining_time":6.631066507},
{"learn":[0.3553544594],"iteration":553,"passed_time":8.219563368,"remaining_time":6.617193614},
{"learn":[0.3553215974],"iteration":554,"passed_time":8.23505102,"remaining_time":6.602878746},
{"learn":[0.3553100157],"iteration":555,"passed_time":8.249965279,"remaining_time":6.588101769},
{"learn":[0.3552437773],"iteration":556,"passed_time":8.264965237,"remaining_time":6.57339246},
{"learn":[0.3552263745],"iteration":557,"passed_time":8.281536074,"remaining_time":6.559926424},
{"learn":[0.3552011387],"iteration":558,"passed_time":8.295251574,"remaining_time":6.54419668},
{"learn":[0.3551712961],"iteration":559,"passed_time":8.309621694,"remaining_time":6.528988474},
{"learn":[0.3551462253],"iteration":560,"passed_time":8.325860172,"remaining_time":6.515245304},
{"learn":[0.3550836853],"iteration":561,"passed_time":8.341504564,"remaining_time":6.501030248},
{"learn":[0.3550645686],"iteration":562,"passed_time":8.352529936,"remaining_time":6.483224835},
{"learn":[0.3550494642],"iteration":563,"passed_time":8.365323264,"remaining_time":6.466810183},
{"learn":[0.3550299479],"iteration":564,"passed_time":8.380693106,"remaining_time":6.452392037},
{"learn":[0.3550235919],"iteration":565,"passed_time":8.395655399,"remaining_time":6.437658027},
{"learn":[0.3549757746],"iteration":566,"passed_time":8.413742902,"remaining_time":6.425309835},
{"learn":[0.3549695072],"iteration":567,"passed_time":8.430364475,"remaining_time":6.411826502},
{"learn":[0.3549443753],"iteration":568,"passed_time":8.451043373,"remaining_time":6.401405437},
{"learn":[0.3549385766],"iteration":569,"passed_time":8.465586056,"remaining_time":6.386319305},
{"learn":[0.3549098251],"iteration":570,"passed_time":8.480262397,"remaining_time":6.371335496},
{"learn":[0.3548791984],"iteration":571,"passed_time":8.493337884,"remaining_time":6.35515492},
{"learn":[0.3548651006],"iteration":572,"passed_time":8.507313248,"remaining_time":6.339655771},
{"learn":[0.354843825],"iteration":573,"passed_time":8.520262667,"remaining_time":6.323400516},
{"learn":[0.3548270683],"iteration":574,"passed_time":8.534978347,"remaining_time":6.308462257},
{"learn":[0.3547852667],"iteration":575,"passed_time":8.549333342,"remaining_time":6.293259266},
{"learn":[0.3547195255],"iteration":576,"passed_time":8.565849634,"remaining_time":6.279643666},
{"learn":[0.3546853285],"iteration":577,"passed_time":8.582439807,"remaining_time":6.26607197},
{"learn":[0.3546223887],"iteration":578,"passed_time":8.598562397,"remaining_time":6.252149861},
{"learn":[0.3546185734],"iteration":579,"passed_time":8.614150113,"remaining_time":6.237832841},
{"learn":[0.3545887856],"iteration":580,"passed_time":8.63104993,"remaining_time":6.224457695},
{"learn":[0.3545613536],"iteration":581,"passed_time":8.646322859,"remaining_time":6.209901984},
{"learn":[0.3545313559],"iteration":582,"passed_time":8.661364093,"remaining_time":6.19517809},
{"learn":[0.3544987757],"iteration":583,"passed_time":8.677255721,"remaining_time":6.18105887},
{"learn":[0.3544758937],"iteration":584,"passed_time":8.691657539,"remaining_time":6.165876716},
{"learn":[0.3544440652],"iteration":585,"passed_time":8.707009828,"remaining_time":6.151368718},
{"learn":[0.3543637537],"iteration":586,"passed_time":8.723053079,"remaining_time":6.137343989},
{"learn":[0.3543093208],"iteration":587,"passed_time":8.738598786,"remaining_time":6.122963775},
{"learn":[0.3542655892],"iteration":588,"passed_time":8.754170315,"remaining_time":6.108597622},
{"learn":[0.3542022305],"iteration":589,"passed_time":8.765492309,"remaining_time":6.091274316},
{"learn":[0.3541965193],"iteration":590,"passed_time":8.77927658,"remaining_time":6.075675332},
{"learn":[0.3541815042],"iteration":591,"passed_time":8.792568464,"remaining_time":6.059743131},
{"learn":[0.3541605789],"iteration":592,"passed_time":8.804784891,"remaining_time":6.043081704},
{"learn":[0.3541059827],"iteration":593,"passed_time":8.818901877,"remaining_time":6.02773428},
{"learn":[0.3540720808],"iteration":594,"passed_time":8.832870171,"remaining_time":6.01228978},
{"learn":[0.354052787],"iteration":595,"passed_time":8.848240437,"remaining_time":5.997800564},
{"learn":[0.3540479158],"iteration":596,"passed_time":8.860187044,"remaining_time":5.980997285},
{"learn":[0.354043286],"iteration":597,"passed_time":8.871542526,"remaining_time":5.963812869},
{"learn":[0.3540290706],"iteration":598,"passed_time":8.886588316,"remaining_time":5.949118388},
{"learn":[0.3539843485],"iteration":599,"passed_time":8.900807996,"remaining_time":5.933871998},
{"learn":[0.353962099],"iteration":600,"passed_time":8.915108207,"remaining_time":5.918682487},
{"learn":[0.3539446506],"iteration":601,"passed_time":8.927178524,"remaining_time":5.902021682},
{"learn":[0.3539165259],"iteration":602,"passed_time":8.941440521,"remaining_time":5.88681905},
{"learn":[0.3538662995],"iteration":603,"passed_time":8.956250528,"remaining_time":5.871978823},
{"learn":[0.3538563618],"iteration":604,"passed_time":8.971682055,"remaining_time":5.857544482},
{"learn":[0.3538448712],"iteration":605,"passed_time":8.98647942,"remaining_time":5.842694541},
{"learn":[0.3538061764],"iteration":606,"passed_time":9.00109704,"remaining_time":5.827728396},
{"learn":[0.3537392339],"iteration":607,"passed_time":9.01596619,"remaining_time":5.81292557},
{"learn":[0.3536841824],"iteration":608,"passed_time":9.029630009,"remaining_time":5.797348659},
{"learn":[0.3536543414],"iteration":609,"passed_time":9.043753235,"remaining_time":5.78207174},
{"learn":[0.3536291713],"iteration":610,"passed_time":9.058686778,"remaining_time":5.767314495},
{"learn":[0.3536186909],"iteration":611,"passed_time":9.069942496,"remaining_time":5.750224981},
{"learn":[0.3535858193],"iteration":612,"passed_time":9.084852356,"remaining_time":5.735461438},
{"learn":[0.3535621482],"iteration":613,"passed_time":9.097795389,"remaining_time":5.719460945},
{"learn":[0.3535575235],"iteration":614,"passed_time":9.112216198,"remaining_time":5.704395506},
{"learn":[0.35355197],"iteration":615,"passed_time":9.129379188,"remaining_time":5.691041572},
{"learn":[0.3535462309],"iteration":616,"passed_time":9.146674201,"remaining_time":5.677757243},
{"learn":[0.3535027918],"iteration":617,"passed_time":9.162426446,"remaining_time":5.663506314},
{"learn":[0.3534898302],"iteration":618,"passed_time":9.179640519,"remaining_time":5.650150303},
{"learn":[0.3534825182],"iteration":619,"passed_time":9.199047557,"remaining_time":5.638125922},
{"learn":[0.3534519629],"iteration":620,"passed_time":9.214778093,"remaining_time":5.623833973},
{"learn":[0.3534349943],"iteration":621,"passed_time":9.231215336,"remaining_time":5.609966877},
{"learn":[0.3533863157],"iteration":622,"passed_time":9.246202943,"remaining_time":5.595214301},
{"learn":[0.3533815969],"iteration":623,"passed_time":9.261493316,"remaining_time":5.580643408},
{"learn":[0.3533645676],"iteration":624,"passed_time":9.277526608,"remaining_time":5.566515965},
{"learn":[0.3533523348],"iteration":625,"passed_time":9.291599006,"remaining_time":5.551210907},
{"learn":[0.353320981],"iteration":626,"passed_time":9.305754254,"remaining_time":5.53595907},
{"learn":[0.3533103981],"iteration":627,"passed_time":9.319949025,"remaining_time":5.520734136},
{"learn":[0.3532924282],"iteration":628,"passed_time":9.336712414,"remaining_time":5.507027513},
{"learn":[0.3532517554],"iteration":629,"passed_time":9.351580295,"remaining_time":5.492197951},
{"learn":[0.353247687],"iteration":630,"passed_time":9.365460897,"remaining_time":5.476790921},
{"learn":[0.3532359805],"iteration":631,"passed_time":9.37920952,"remaining_time":5.461311873},
{"learn":[0.3532291229],"iteration":632,"passed_time":9.392357638,"remaining_time":5.445490131},
{"learn":[0.3532184555],"iteration":633,"passed_time":9.404901562,"remaining_time":5.429328031},
{"learn":[0.3531908968],"iteration":634,"passed_time":9.419234895,"remaining_time":5.414205884},
{"learn":[0.3531798409],"iteration":635,"passed_time":9.434516349,"remaining_time":5.399628854},
{"learn":[0.353162959],"iteration":636,"passed_time":9.446526705,"remaining_time":5.383185547},
{"learn":[0.3531591434],"iteration":637,"passed_time":9.458880464,"remaining_time":5.366950984},
{"learn":[0.3531205947],"iteration":638,"passed_time":9.471831181,"remaining_time":5.351065816},
{"learn":[0.3531096929],"iteration":639,"passed_time":9.483727959,"remaining_time":5.334596977},
{"learn":[0.3531009362],"iteration":640,"passed_time":9.496766681,"remaining_time":5.318781963},
{"learn":[0.3530754525],"iteration":641,"passed_time":9.511777198,"remaining_time":5.304075135},
{"learn":[0.3529951356],"iteration":642,"passed_time":9.526787826,"remaining_time":5.289367424},
{"learn":[0.3529442728],"iteration":643,"passed_time":9.539971597,"remaining_time":5.273648895},
{"learn":[0.352924322],"iteration":644,"passed_time":9.551372186,"remaining_time":5.256956784},
{"learn":[0.3529034848],"iteration":645,"passed_time":9.564959352,"remaining_time":5.241479274},
{"learn":[0.3528856304],"iteration":646,"passed_time":9.577157706,"remaining_time":5.225249877},
{"learn":[0.352878412],"iteration":647,"passed_time":9.593148432,"remaining_time":5.211092975},
{"learn":[0.352870818],"iteration":648,"passed_time":9.608707892,"remaining_time":5.19669718},
{"learn":[0.3528510608],"iteration":649,"passed_time":9.624219611,"remaining_time":5.182272098},
{"learn":[0.3528328745],"iteration":650,"passed_time":9.636855232,"remaining_time":5.166301806},
{"learn":[0.3527865192],"iteration":651,"passed_time":9.651146199,"remaining_time":5.151225272},
{"learn":[0.352774216],"iteration":652,"passed_time":9.663870511,"remaining_time":5.135318633},
{"learn":[0.3527446631],"iteration":653,"passed_time":9.674626312,"remaining_time":5.118380281},
{"learn":[0.3527184598],"iteration":654,"passed_time":9.686866921,"remaining_time":5.102242882},
{"learn":[0.3527110461],"iteration":655,"passed_time":9.700842876,"remaining_time":5.087027362},
{"learn":[0.3526957345],"iteration":656,"passed_time":9.712844744,"remaining_time":5.070785003},
{"learn":[0.3526755943],"iteration":657,"passed_time":9.726135466,"remaining_time":5.055225424},
{"learn":[0.3526619178],"iteration":658,"passed_time":9.7415871,"remaining_time":5.040790897},
{"learn":[0.3526497527],"iteration":659,"passed_time":9.783935985,"remaining_time":5.040209447},
{"learn":[0.3526190249],"iteration":660,"passed_time":9.797839029,"remaining_time":5.024912906},
{"learn":[0.3526067082],"iteration":661,"passed_time":9.81233018,"remaining_time":5.009920847},
{"learn":[0.3525697492],"iteration":662,"passed_time":9.830364323,"remaining_time":4.996731187},
{"learn":[0.352560642],"iteration":663,"passed_time":9.846045575,"remaining_time":4.982336315},
{"learn":[0.3525404099],"iteration":664,"passed_time":9.860055243,"remaining_time":4.967095498},
{"learn":[0.3525373436],"iteration":665,"passed_time":9.873922452,"remaining_time":4.951786936},
{"learn":[0.3525120847],"iteration":666,"passed_time":9.888863483,"remaining_time":4.937018801},
{"learn":[0.3524826422],"iteration":667,"passed_time":9.901708179,"remaining_time":4.921208256},
{"learn":[0.3524663778],"iteration":668,"passed_time":9.915201457,"remaining_time":4.905727477},
{"learn":[0.3524620063],"iteration":669,"passed_time":9.928554011,"remaining_time":4.890183319},
{"learn":[0.3524210423],"iteration":670,"passed_time":9.94356513,"remaining_time":4.875458909},
{"learn":[0.3523952937],"iteration":671,"passed_time":9.957928659,"remaining_time":4.86041756},
{"learn":[0.3523602205],"iteration":672,"passed_time":9.97283836,"remaining_time":4.845643602},
{"learn":[0.3523546337],"iteration":673,"passed_time":9.987151907,"remaining_time":4.830580893},
{"learn":[0.3523443017],"iteration":674,"passed_time":10.00060521,"remaining_time":4.81510621},
{"learn":[0.3523123765],"iteration":675,"passed_time":10.01537076,"remaining_time":4.80026646},
{"learn":[0.3522439795],"iteration":676,"passed_time":10.02996307,"remaining_time":4.785344272},
{"learn":[0.3522294169],"iteration":677,"passed_time":10.0434542,"remaining_time":4.769900075},
{"learn":[0.3522096061],"iteration":678,"passed_time":10.0570572,"remaining_time":4.754514522},
{"learn":[0.3521953615],"iteration":679,"passed_time":10.06853555,"remaining_time":4.738134375},
{"learn":[0.3521788847],"iteration":680,"passed_time":10.08407332,"remaining_time":4.723670174},
{"learn":[0.352176507],"iteration":681,"passed_time":10.09883655,"remaining_time":4.708841678},
{"learn":[0.3521737412],"iteration":682,"passed_time":10.11242862,"remaining_time":4.693469801},
{"learn":[0.3521541753],"iteration":683,"passed_time":10.12658268,"remaining_time":4.678362757},
{"learn":[0.3521345335],"iteration":684,"passed_time":10.14007548,"remaining_time":4.662954417},
{"learn":[0.3521162855],"iteration":685,"passed_time":10.15617637,"remaining_time":4.648745452},
{"learn":[0.3520903982],"iteration":686,"passed_time":10.17164475,"remaining_time":4.634242805},
{"learn":[0.3520867854],"iteration":687,"passed_time":10.18497616,"remaining_time":4.618768259},
{"learn":[0.3520599641],"iteration":688,"passed_time":10.20072781,"remaining_time":4.604392378},
{"learn":[0.3520499871],"iteration":689,"passed_time":10.2149107,"remaining_time":4.589307707},
{"learn":[0.3520329417],"iteration":690,"passed_time":10.22857992,"remaining_time":4.57399594},
{"learn":[0.3519853467],"iteration":691,"passed_time":10.24261592,"remaining_time":4.558852175},
{"learn":[0.3519670036],"iteration":692,"passed_time":10.25440697,"remaining_time":4.542717083},
{"learn":[0.3519401749],"iteration":693,"passed_time":10.26650943,"remaining_time":4.526731824},
{"learn":[0.3519276326],"iteration":694,"passed_time":10.28056623,"remaining_time":4.511615396},
{"learn":[0.3519037585],"iteration":695,"passed_time":10.2922639,"remaining_time":4.495471588},
{"learn":[0.3518934218],"iteration":696,"passed_time":10.30352202,"remaining_time":4.479149457},
{"learn":[0.3518723434],"iteration":697,"passed_time":10.31786372,"remaining_time":4.464175994},
{"learn":[0.35183687],"iteration":698,"passed_time":10.33112061,"remaining_time":4.448737201},
{"learn":[0.3518073809],"iteration":699,"passed_time":10.34250645,"remaining_time":4.432502765},
{"learn":[0.351785325],"iteration":700,"passed_time":10.35643046,"remaining_time":4.417364774},
{"learn":[0.3517663331],"iteration":701,"passed_time":10.36940119,"remaining_time":4.401825575},
{"learn":[0.3517490165],"iteration":702,"passed_time":10.38402555,"remaining_time":4.386992303},
{"learn":[0.3517312181],"iteration":703,"passed_time":10.3979503,"remaining_time":4.371865466},
{"learn":[0.3517049599],"iteration":704,"passed_time":10.41017964,"remaining_time":4.356032617},
{"learn":[0.3516969547],"iteration":705,"passed_time":10.42386838,"remaining_time":4.340817712},
{"learn":[0.3516774267],"iteration":706,"passed_time":10.43555194,"remaining_time":4.324776123},
{"learn":[0.3516727603],"iteration":707,"passed_time":10.44836956,"remaining_time":4.309214565},
{"learn":[0.3516661595],"iteration":708,"passed_time":10.46285937,"remaining_time":4.294347076},
{"learn":[0.3516308056],"iteration":709,"passed_time":10.4767218,"remaining_time":4.279224396},
{"learn":[0.3516111465],"iteration":710,"passed_time":10.49166286,"remaining_time":4.264543693},
{"learn":[0.3515937674],"iteration":711,"passed_time":10.50351315,"remaining_time":4.248612062},
{"learn":[0.3515461444],"iteration":712,"passed_time":10.51786924,"remaining_time":4.23370052},
{"learn":[0.3515266542],"iteration":713,"passed_time":10.53150211,"remaining_time":4.218500846},
{"learn":[0.3515150653],"iteration":714,"passed_time":10.54575277,"remaining_time":4.203551804},
{"learn":[0.3515125516],"iteration":715,"passed_time":10.55753959,"remaining_time":4.187627433},
{"learn":[0.3514971095],"iteration":716,"passed_time":10.57174231,"remaining_time":4.172668166},
{"learn":[0.3514751189],"iteration":717,"passed_time":10.58493449,"remaining_time":4.157314105},
{"learn":[0.3514491508],"iteration":718,"passed_time":10.59797706,"remaining_time":4.141907587},
{"learn":[0.3514300185],"iteration":719,"passed_time":10.61142873,"remaining_time":4.126666727},
{"learn":[0.3514109388],"iteration":720,"passed_time":10.62412542,"remaining_time":4.111138687},
{"learn":[0.3513776258],"iteration":721,"passed_time":10.63932747,"remaining_time":4.096583153},
{"learn":[0.3513680603],"iteration":722,"passed_time":10.65397389,"remaining_time":4.081812958},
{"learn":[0.351341205],"iteration":723,"passed_time":10.66817106,"remaining_time":4.066871839},
{"learn":[0.3513238872],"iteration":724,"passed_time":10.68330018,"remaining_time":4.052286274},
{"learn":[0.3512961071],"iteration":725,"passed_time":10.69719104,"remaining_time":4.037231882},
{"learn":[0.3512788745],"iteration":726,"passed_time":10.71312365,"remaining_time":4.022947397},
{"learn":[0.3512606688],"iteration":727,"passed_time":10.72500862,"remaining_time":4.007146077},
{"learn":[0.3512524033],"iteration":728,"passed_time":10.73902458,"remaining_time":3.992147685},
{"learn":[0.351249946],"iteration":729,"passed_time":10.75188417,"remaining_time":3.976724283},
{"learn":[0.3512401143],"iteration":730,"passed_time":10.76579232,"remaining_time":3.961693754},
{"learn":[0.351200202],"iteration":731,"passed_time":10.78138788,"remaining_time":3.947284088},
{"learn":[0.3511379884],"iteration":732,"passed_time":10.7990046,"remaining_time":3.933607406},
{"learn":[0.3511347295],"iteration":733,"passed_time":10.81530683,"remaining_time":3.91944362},
{"learn":[0.3511116848],"iteration":734,"passed_time":10.82593596,"remaining_time":3.903228613},
{"learn":[0.3510874352],"iteration":735,"passed_time":10.83947514,"remaining_time":3.888072606},
{"learn":[0.3510487771],"iteration":736,"passed_time":10.85372638,"remaining_time":3.873175084},
{"learn":[0.3510232911],"iteration":737,"passed_time":10.86792966,"remaining_time":3.858262293},
{"learn":[0.3510008771],"iteration":738,"passed_time":10.88331658,"remaining_time":3.843769457},
{"learn":[0.3509869868],"iteration":739,"passed_time":10.89694043,"remaining_time":3.828654745},
{"learn":[0.3509692777],"iteration":740,"passed_time":10.91389344,"remaining_time":3.814707692},
{"learn":[0.3509380248],"iteration":741,"passed_time":10.92955072,"remaining_time":3.800302002},
{"learn":[0.3509211167],"iteration":742,"passed_time":10.9455664,"remaining_time":3.786016912},
{"learn":[0.3509109203],"iteration":743,"passed_time":10.96062631,"remaining_time":3.771398301},
{"learn":[0.3509035476],"iteration":744,"passed_time":10.976028,"remaining_time":3.756895489},
{"learn":[0.3508716502],"iteration":745,"passed_time":10.99258115,"remaining_time":3.742782323},
{"learn":[0.3508622157],"iteration":746,"passed_time":11.0084591,"remaining_time":3.72843394},
{"learn":[0.3508415078],"iteration":747,"passed_time":11.02360001,"remaining_time":3.713833157},
{"learn":[0.3508376207],"iteration":748,"passed_time":11.03856485,"remaining_time":3.699171931},
{"learn":[0.3508261471],"iteration":749,"passed_time":11.05472502,"remaining_time":3.68490834},
{"learn":[0.3508077213],"iteration":750,"passed_time":11.06712751,"remaining_time":3.669393808},
{"learn":[0.3507947602],"iteration":751,"passed_time":11.08288467,"remaining_time":3.654993879},
{"learn":[0.350780484],"iteration":752,"passed_time":11.09781838,"remaining_time":3.640320239},
{"learn":[0.3507627588],"iteration":753,"passed_time":11.11395658,"remaining_time":3.626038884},
{"learn":[0.3507391092],"iteration":754,"passed_time":11.12762147,"remaining_time":3.610950014},
{"learn":[0.3507225993],"iteration":755,"passed_time":11.14235917,"remaining_time":3.59621116},
{"learn":[0.3507100834],"iteration":756,"passed_time":11.15525549,"remaining_time":3.580881219},
{"learn":[0.3507028791],"iteration":757,"passed_time":11.16880513,"remaining_time":3.56576628},
{"learn":[0.3506860631],"iteration":758,"passed_time":11.18228498,"remaining_time":3.550633306},
{"learn":[0.350675074],"iteration":759,"passed_time":11.19585205,"remaining_time":3.535532225},
{"learn":[0.3506581105],"iteration":760,"passed_time":11.21010824,"remaining_time":3.520651601},
{"learn":[0.3506148956],"iteration":761,"passed_time":11.22445793,"remaining_time":3.505801822},
{"learn":[0.350567837],"iteration":762,"passed_time":11.2393568,"remaining_time":3.491123933},
{"learn":[0.3505367373],"iteration":763,"passed_time":11.25610064,"remaining_time":3.477015381},
{"learn":[0.350534749],"iteration":764,"passed_time":11.27068689,"remaining_time":3.462237149},
{"learn":[0.3505203856],"iteration":765,"passed_time":11.28411868,"remaining_time":3.447106752},
{"learn":[0.3505135842],"iteration":766,"passed_time":11.29724382,"remaining_time":3.431887628},
{"learn":[0.3505044981],"iteration":767,"passed_time":11.31041921,"remaining_time":3.416689138},
{"learn":[0.3504833833],"iteration":768,"passed_time":11.32193242,"remaining_time":3.400996604},
{"learn":[0.3504521725],"iteration":769,"passed_time":11.33843632,"remaining_time":3.386805654},
{"learn":[0.3504111334],"iteration":770,"passed_time":11.35296557,"remaining_time":3.3720222},
{"learn":[0.3503960172],"iteration":771,"passed_time":11.36634308,"remaining_time":3.356899251},
{"learn":[0.3503674965],"iteration":772,"passed_time":11.3805738,"remaining_time":3.342031375},
{"learn":[0.350363926],"iteration":773,"passed_time":11.39575126,"remaining_time":3.327441583},
{"learn":[0.3503596566],"iteration":774,"passed_time":11.41142862,"remaining_time":3.312995406},
{"learn":[0.3503270662],"iteration":775,"passed_time":11.42876058,"remaining_time":3.299023672},
{"learn":[0.3503089272],"iteration":776,"passed_time":11.44033865,"remaining_time":3.283391916},
{"learn":[0.3502544539],"iteration":777,"passed_time":11.45457506,"remaining_time":3.268529129},
{"learn":[0.3502417639],"iteration":778,"passed_time":11.46854895,"remaining_time":3.253593477},
{"learn":[0.3501864958],"iteration":779,"passed_time":11.48077265,"remaining_time":3.238166644},
{"learn":[0.3501439825],"iteration":780,"passed_time":11.49235434,"remaining_time":3.22256799},
{"learn":[0.3501071036],"iteration":781,"passed_time":11.50699145,"remaining_time":3.207831375},
{"learn":[0.350103948],"iteration":782,"passed_time":11.5190851,"remaining_time":3.192390124},
{"learn":[0.3500940057],"iteration":783,"passed_time":11.52993493,"remaining_time":3.176614726},
{"learn":[0.350087816],"iteration":784,"passed_time":11.54211947,"remaining_time":3.161217434},
{"learn":[0.3500703801],"iteration":785,"passed_time":11.5527936,"remaining_time":3.145417086},
{"learn":[0.3500382044],"iteration":786,"passed_time":11.56383349,"remaining_time":3.12972876},
{"learn":[0.3500106146],"iteration":787,"passed_time":11.57350433,"remaining_time":3.113683905},
{"learn":[0.3499974974],"iteration":788,"passed_time":11.58694604,"remaining_time":3.098663643},
{"learn":[0.3499935264],"iteration":789,"passed_time":11.60017522,"remaining_time":3.083590881},
{"learn":[0.3499850473],"iteration":790,"passed_time":11.61049156,"remaining_time":3.067753142},
{"learn":[0.3499699583],"iteration":791,"passed_time":11.62172902,"remaining_time":3.052171257},
{"learn":[0.3499474584],"iteration":792,"passed_time":11.63381697,"remaining_time":3.036822335},
{"learn":[0.3499307515],"iteration":793,"passed_time":11.64693429,"remaining_time":3.021748694},
{"learn":[0.3498962095],"iteration":794,"passed_time":11.65748105,"remaining_time":3.006017126},
{"learn":[0.3498876632],"iteration":795,"passed_time":11.66888063,"remaining_time":2.990517145},
{"learn":[0.3498796769],"iteration":796,"passed_time":11.6812058,"remaining_time":2.975263209},
{"learn":[0.3498567639],"iteration":797,"passed_time":11.69218239,"remaining_time":2.959675242},
{"learn":[0.3498282504],"iteration":798,"passed_time":11.70275094,"remaining_time":2.943996169},
{"learn":[0.3497847975],"iteration":799,"passed_time":11.7161899,"remaining_time":2.929047475},
{"learn":[0.3497770349],"iteration":800,"passed_time":11.73156187,"remaining_time":2.914582786},
{"learn":[0.3497527076],"iteration":801,"passed_time":11.74615235,"remaining_time":2.8999229},
{"learn":[0.3497429293],"iteration":802,"passed_time":11.76015798,"remaining_time":2.885119703},
{"learn":[0.3497182361],"iteration":803,"passed_time":11.7747591,"remaining_time":2.870463662},
{"learn":[0.3496810489],"iteration":804,"passed_time":11.78768974,"remaining_time":2.855403104},
{"learn":[0.3496709796],"iteration":805,"passed_time":11.80319411,"remaining_time":2.840967317},
{"learn":[0.3496466321],"iteration":806,"passed_time":11.81783874,"remaining_time":2.826323268},
{"learn":[0.3496117771],"iteration":807,"passed_time":11.83237838,"remaining_time":2.811654269},
{"learn":[0.3495995212],"iteration":808,"passed_time":11.85039158,"remaining_time":2.797805676},
{"learn":[0.3495922845],"iteration":809,"passed_time":11.86260185,"remaining_time":2.782585619},
{"learn":[0.3495662293],"iteration":810,"passed_time":11.87543847,"remaining_time":2.767518953},
{"learn":[0.3495431573],"iteration":811,"passed_time":11.88931777,"remaining_time":2.752699187},
{"learn":[0.3495248764],"iteration":812,"passed_time":11.90095837,"remaining_time":2.737366809},
{"learn":[0.3494957089],"iteration":813,"passed_time":11.91338309,"remaining_time":2.722222671},
{"learn":[0.3494880371],"iteration":814,"passed_time":11.92521864,"remaining_time":2.70695147},
{"learn":[0.3494847342],"iteration":815,"passed_time":11.9368653,"remaining_time":2.691646097},
{"learn":[0.3494805899],"iteration":816,"passed_time":11.94681019,"remaining_time":2.675968501},
{"learn":[0.3494510989],"iteration":817,"passed_time":11.96100528,"remaining_time":2.661250563},
{"learn":[0.349415067],"iteration":818,"passed_time":11.97471496,"remaining_time":2.646426626},
{"learn":[0.3493902053],"iteration":819,"passed_time":11.98761552,"remaining_time":2.631427798},
{"learn":[0.3493596992],"iteration":820,"passed_time":12.00411696,"remaining_time":2.617219166},
{"learn":[0.3493384545],"iteration":821,"passed_time":12.01744706,"remaining_time":2.60231822},
{"learn":[0.349312713],"iteration":822,"passed_time":12.03191552,"remaining_time":2.587665914},
{"learn":[0.3492973225],"iteration":823,"passed_time":12.04759861,"remaining_time":2.57327349},
{"learn":[0.3492906663],"iteration":824,"passed_time":12.06214774,"remaining_time":2.5586374},
{"learn":[0.3492706906],"iteration":825,"passed_time":12.07776808,"remaining_time":2.544227175},
{"learn":[0.3492635987],"iteration":826,"passed_time":12.09128565,"remaining_time":2.529374144},
{"learn":[0.349255609],"iteration":827,"passed_time":12.10494823,"remaining_time":2.514554463},
{"learn":[0.3492216172],"iteration":828,"passed_time":12.11768179,"remaining_time":2.499545942},
{"learn":[0.3491987883],"iteration":829,"passed_time":12.13334293,"remaining_time":2.485142527},
{"learn":[0.3491735552],"iteration":830,"passed_time":12.14855494,"remaining_time":2.470644748},
{"learn":[0.3491616321],"iteration":831,"passed_time":12.16084475,"remaining_time":2.455555189},
{"learn":[0.349148027],"iteration":832,"passed_time":12.17452889,"remaining_time":2.44075189},
{"learn":[0.3491310884],"iteration":833,"passed_time":12.18941134,"remaining_time":2.426189788},
{"learn":[0.3491087556],"iteration":834,"passed_time":12.2025015,"remaining_time":2.411272752},
{"learn":[0.349100514],"iteration":835,"passed_time":12.21495847,"remaining_time":2.396235873},
{"learn":[0.3490893816],"iteration":836,"passed_time":12.22948781,"remaining_time":2.381608737},
{"learn":[0.3490564927],"iteration":837,"passed_time":12.24590636,"remaining_time":2.367347052},
{"learn":[0.3490413287],"iteration":838,"passed_time":12.26084292,"remaining_time":2.35279584},
{"learn":[0.3490171919],"iteration":839,"passed_time":12.27644557,"remaining_time":2.338370585},
{"learn":[0.3490031557],"iteration":840,"passed_time":12.29068413,"remaining_time":2.323684634},
{"learn":[0.3490006817],"iteration":841,"passed_time":12.30170012,"remaining_time":2.308395034},
{"learn":[0.3489921278],"iteration":842,"passed_time":12.31360152,"remaining_time":2.293280473},
{"learn":[0.3489864687],"iteration":843,"passed_time":12.32625629,"remaining_time":2.278312774},
{"learn":[0.3489653935],"iteration":844,"passed_time":12.33902667,"remaining_time":2.263371757},
{"learn":[0.3489400081],"iteration":845,"passed_time":12.34985403,"remaining_time":2.248082176},
{"learn":[0.3489207483],"iteration":846,"passed_time":12.36403788,"remaining_time":2.23340944},
{"learn":[0.3488982589],"iteration":847,"passed_time":12.37744965,"remaining_time":2.218599466},
{"learn":[0.3488850449],"iteration":848,"passed_time":12.39161475,"remaining_time":2.20392677},
{"learn":[0.3488688701],"iteration":849,"passed_time":12.4030779,"remaining_time":2.188778453},
{"learn":[0.3488583401],"iteration":850,"passed_time":12.41523065,"remaining_time":2.173759538},
{"learn":[0.3488229158],"iteration":851,"passed_time":12.42910401,"remaining_time":2.159046236},
{"learn":[0.3487741592],"iteration":852,"passed_time":12.44301073,"remaining_time":2.144340654},
{"learn":[0.3487472666],"iteration":853,"passed_time":12.45344168,"remaining_time":2.129042723},
{"learn":[0.3487167296],"iteration":854,"passed_time":12.46707795,"remaining_time":2.11429977},
{"learn":[0.3487030832],"iteration":855,"passed_time":12.47945474,"remaining_time":2.099347526},
{"learn":[0.348697638],"iteration":856,"passed_time":12.49229093,"remaining_time":2.084477949},
{"learn":[0.3486912851],"iteration":857,"passed_time":12.50574019,"remaining_time":2.069714577},
{"learn":[0.3486881252],"iteration":858,"passed_time":12.51923567,"remaining_time":2.05496185},
{"learn":[0.3486642103],"iteration":859,"passed_time":12.53189406,"remaining_time":2.040075777},
{"learn":[0.3486569379],"iteration":860,"passed_time":12.54697799,"remaining_time":2.025586458},
{"learn":[0.3486445442],"iteration":861,"passed_time":12.55783822,"remaining_time":2.010419576},
{"learn":[0.3486264014],"iteration":862,"passed_time":12.56972885,"remaining_time":1.995426248},
{"learn":[0.3485984724],"iteration":863,"passed_time":12.58464712,"remaining_time":1.980916677},
{"learn":[0.3485631898],"iteration":864,"passed_time":12.59915116,"remaining_time":1.96634151},
{"learn":[0.348552808],"iteration":865,"passed_time":12.61371955,"remaining_time":1.951776467},
{"learn":[0.3485078594],"iteration":866,"passed_time":12.62692356,"remaining_time":1.937002114},
{"learn":[0.3484878546],"iteration":867,"passed_time":12.64211225,"remaining_time":1.9225332},
{"learn":[0.348484991],"iteration":868,"passed_time":12.65537283,"remaining_time":1.907771969},
{"learn":[0.3484551773],"iteration":869,"passed_time":12.66874073,"remaining_time":1.893030223},
{"learn":[0.3484345617],"iteration":870,"passed_time":12.68108432,"remaining_time":1.878139928},
{"learn":[0.3484126646],"iteration":871,"passed_time":12.69485501,"remaining_time":1.863464956},
{"learn":[0.3483641507],"iteration":872,"passed_time":12.70657249,"remaining_time":1.848493363},
{"learn":[0.3483481524],"iteration":873,"passed_time":12.72155015,"remaining_time":1.83399922},
{"learn":[0.3483406039],"iteration":874,"passed_time":12.73583206,"remaining_time":1.819404579},
{"learn":[0.3483243017],"iteration":875,"passed_time":12.74978214,"remaining_time":1.804763682},
{"learn":[0.348312653],"iteration":876,"passed_time":12.76210392,"remaining_time":1.789895989},
{"learn":[0.3483037517],"iteration":877,"passed_time":12.77695501,"remaining_time":1.775385548},
{"learn":[0.3483012856],"iteration":878,"passed_time":12.79111105,"remaining_time":1.760778654},
{"learn":[0.3482781148],"iteration":879,"passed_time":12.80608629,"remaining_time":1.746284494},
{"learn":[0.3482497324],"iteration":880,"passed_time":12.82193724,"remaining_time":1.731907527},
{"learn":[0.3482233888],"iteration":881,"passed_time":12.83705304,"remaining_time":1.717428865},
{"learn":[0.3481981758],"iteration":882,"passed_time":12.85243035,"remaining_time":1.70298341},
{"learn":[0.34819403],"iteration":883,"passed_time":12.86658801,"remaining_time":1.688375802},
{"learn":[0.3481877789],"iteration":884,"passed_time":12.87986506,"remaining_time":1.673654782},
{"learn":[0.3481573721],"iteration":885,"passed_time":12.89238734,"remaining_time":1.658839906},
{"learn":[0.348135454],"iteration":886,"passed_time":12.9063215,"remaining_time":1.644210068},
{"learn":[0.3481268982],"iteration":887,"passed_time":12.92137208,"remaining_time":1.629722604},
{"learn":[0.3481074133],"iteration":888,"passed_time":12.9358528,"remaining_time":1.615162723},
{"learn":[0.34809654],"iteration":889,"passed_time":12.948415,"remaining_time":1.600365898},
{"learn":[0.3480808041],"iteration":890,"passed_time":12.96401228,"remaining_time":1.585945385},
{"learn":[0.3480587628],"iteration":891,"passed_time":12.97937177,"remaining_time":1.571493443},
{"learn":[0.3480384281],"iteration":892,"passed_time":12.99492953,"remaining_time":1.557063225},
{"learn":[0.3480052083],"iteration":893,"passed_time":13.01030038,"remaining_time":1.542608323},
{"learn":[0.3479748449],"iteration":894,"passed_time":13.02523942,"remaining_time":1.528100714},
{"learn":[0.3479719317],"iteration":895,"passed_time":13.04051245,"remaining_time":1.513630909},
{"learn":[0.3479658804],"iteration":896,"passed_time":13.05703416,"remaining_time":1.499302697},
{"learn":[0.3479405613],"iteration":897,"passed_time":13.07174794,"remaining_time":1.484764242},
{"learn":[0.3479321598],"iteration":898,"passed_time":13.08503625,"remaining_time":1.470065251},
{"learn":[0.3479114435],"iteration":899,"passed_time":13.09849154,"remaining_time":1.455387949},
{"learn":[0.347902161],"iteration":900,"passed_time":13.11280362,"remaining_time":1.440807501},
{"learn":[0.3478853635],"iteration":901,"passed_time":13.12921798,"remaining_time":1.426456056},
{"learn":[0.3478803864],"iteration":902,"passed_time":13.14410761,"remaining_time":1.411936255},
{"learn":[0.3478582343],"iteration":903,"passed_time":13.16041404,"remaining_time":1.397566092},
{"learn":[0.3478384165],"iteration":904,"passed_time":13.17450112,"remaining_time":1.382958681},
{"learn":[0.3478356494],"iteration":905,"passed_time":13.18936258,"remaining_time":1.368432763},
{"learn":[0.3478276527],"iteration":906,"passed_time":13.20795147,"remaining_time":1.354288299},
{"learn":[0.3477966218],"iteration":907,"passed_time":13.22456235,"remaining_time":1.33993363},
{"learn":[0.3477907442],"iteration":908,"passed_time":13.24205512,"remaining_time":1.325662284},
{"learn":[0.3477760615],"iteration":909,"passed_time":13.26109907,"remaining_time":1.311537271},
{"learn":[0.3477634219],"iteration":910,"passed_time":13.27591337,"remaining_time":1.296988243},
{"learn":[0.3477527623],"iteration":911,"passed_time":13.29159449,"remaining_time":1.282522276},
{"learn":[0.3477277234],"iteration":912,"passed_time":13.30702658,"remaining_time":1.268029915},
{"learn":[0.3476971036],"iteration":913,"passed_time":13.32261698,"remaining_time":1.253550394},
{"learn":[0.3476907348],"iteration":914,"passed_time":13.3390263,"remaining_time":1.239144519},
{"learn":[0.3476740901],"iteration":915,"passed_time":13.35591442,"remaining_time":1.224778178},
{"learn":[0.3476530622],"iteration":916,"passed_time":13.37382449,"remaining_time":1.210498836},
{"learn":[0.3476195908],"iteration":917,"passed_time":13.39068431,"remaining_time":1.196117771},
{"learn":[0.3475987174],"iteration":918,"passed_time":13.40637259,"remaining_time":1.181628052},
{"learn":[0.3475896113],"iteration":919,"passed_time":13.42529184,"remaining_time":1.167416682},
{"learn":[0.3475749496],"iteration":920,"passed_time":13.43971125,"remaining_time":1.152809108},
{"learn":[0.3475726515],"iteration":921,"passed_time":13.45811549,"remaining_time":1.138539055},
{"learn":[0.3475666951],"iteration":922,"passed_time":13.47131346,"remaining_time":1.123825717},
{"learn":[0.3475321564],"iteration":923,"passed_time":13.48976856,"remaining_time":1.109548064},
{"learn":[0.3475168384],"iteration":924,"passed_time":13.50405683,"remaining_time":1.094923527},
{"learn":[0.3474855184],"iteration":925,"passed_time":13.51857426,"remaining_time":1.080318029},
{"learn":[0.3474703707],"iteration":926,"passed_time":13.53481396,"remaining_time":1.065848348},
{"learn":[0.3474464198],"iteration":927,"passed_time":13.54963579,"remaining_time":1.051264846},
{"learn":[0.3474317702],"iteration":928,"passed_time":13.59812943,"remaining_time":1.039254241},
{"learn":[0.3474141654],"iteration":929,"passed_time":13.61934803,"remaining_time":1.025112217},
{"learn":[0.3473980269],"iteration":930,"passed_time":13.6335313,"remaining_time":1.010433576},
{"learn":[0.3473875948],"iteration":931,"passed_time":13.66956933,"remaining_time":0.9973505519},
{"learn":[0.3473640601],"iteration":932,"passed_time":13.69242115,"remaining_time":0.9832714008},
{"learn":[0.3473503303],"iteration":933,"passed_time":13.72541761,"remaining_time":0.9698903234},
{"learn":[0.3473411586],"iteration":934,"passed_time":13.76168476,"remaining_time":0.9566946624},
{"learn":[0.3473223947],"iteration":935,"passed_time":13.87088407,"remaining_time":0.9484365177},
{"learn":[0.3472953997],"iteration":936,"passed_time":13.89574658,"remaining_time":0.9342924595},
{"learn":[0.3472747343],"iteration":937,"passed_time":13.92627829,"remaining_time":0.9205002708},
{"learn":[0.3472613067],"iteration":938,"passed_time":13.97654773,"remaining_time":0.9079546447},
{"learn":[0.3472420107],"iteration":939,"passed_time":14.04983877,"remaining_time":0.8967982197},
{"learn":[0.3472040889],"iteration":940,"passed_time":14.06789486,"remaining_time":0.8820465426},
{"learn":[0.3471822391],"iteration":941,"passed_time":14.1893928,"remaining_time":0.8736568814},
{"learn":[0.3471550955],"iteration":942,"passed_time":14.23126434,"remaining_time":0.8602142816},
{"learn":[0.3471207781],"iteration":943,"passed_time":14.2599867,"remaining_time":0.8459314147},
{"learn":[0.3471143831],"iteration":944,"passed_time":14.29237847,"remaining_time":0.8318315513},
{"learn":[0.347107134],"iteration":945,"passed_time":14.31406784,"remaining_time":0.8170820965},
{"learn":[0.3471026255],"iteration":946,"passed_time":14.33220115,"remaining_time":0.802118966},
{"learn":[0.347075279],"iteration":947,"passed_time":14.3563857,"remaining_time":0.7874810721},
{"learn":[0.3470490916],"iteration":948,"passed_time":14.37939172,"remaining_time":0.7727597235},
{"learn":[0.3470220057],"iteration":949,"passed_time":14.39917853,"remaining_time":0.7578515013},
{"learn":[0.3469701024],"iteration":950,"passed_time":14.41861816,"remaining_time":0.7429151312},
{"learn":[0.3469368653],"iteration":951,"passed_time":14.44250712,"remaining_time":0.7281936364},
{"learn":[0.3469211439],"iteration":952,"passed_time":14.51394174,"remaining_time":0.7157977564},
{"learn":[0.3469189281],"iteration":953,"passed_time":14.57431565,"remaining_time":0.7027447799},
{"learn":[0.3468976975],"iteration":954,"passed_time":14.59327256,"remaining_time":0.6876411152},
{"learn":[0.3468744906],"iteration":955,"passed_time":14.61038626,"remaining_time":0.6724445559},
{"learn":[0.3468667498],"iteration":956,"passed_time":14.62337425,"remaining_time":0.6570586132},
{"learn":[0.3468508713],"iteration":957,"passed_time":14.64718515,"remaining_time":0.6421521674},
{"learn":[0.3468492943],"iteration":958,"passed_time":14.66404969,"remaining_time":0.6269301745},
{"learn":[0.3468403479],"iteration":959,"passed_time":14.68514064,"remaining_time":0.6118808601},
{"learn":[0.3468323404],"iteration":960,"passed_time":14.70685542,"remaining_time":0.5968442885},
{"learn":[0.3468252806],"iteration":961,"passed_time":14.73671978,"remaining_time":0.5821157503},
{"learn":[0.3468141477],"iteration":962,"passed_time":14.76084836,"remaining_time":0.5671353992},
{"learn":[0.3468077629],"iteration":963,"passed_time":14.7795035,"remaining_time":0.551931666},
{"learn":[0.3468020581],"iteration":964,"passed_time":14.80098922,"remaining_time":0.5368234431},
{"learn":[0.3467927095],"iteration":965,"passed_time":14.81601391,"remaining_time":0.5214746097},
{"learn":[0.3467833415],"iteration":966,"passed_time":14.8292564,"remaining_time":0.5060656268},
{"learn":[0.3467727254],"iteration":967,"passed_time":14.84730787,"remaining_time":0.4908200947},
{"learn":[0.3467594764],"iteration":968,"passed_time":14.86350977,"remaining_time":0.4755096005},
{"learn":[0.3467345094],"iteration":969,"passed_time":14.88091698,"remaining_time":0.4602345457},
{"learn":[0.3467217253],"iteration":970,"passed_time":14.89713498,"remaining_time":0.4449195822},
{"learn":[0.346693007],"iteration":971,"passed_time":14.91626694,"remaining_time":0.4296867019},
{"learn":[0.3466765901],"iteration":972,"passed_time":14.93799807,"remaining_time":0.414517932},
{"learn":[0.3466713261],"iteration":973,"passed_time":14.97203751,"remaining_time":0.3996642456},
{"learn":[0.3466669634],"iteration":974,"passed_time":15.01558108,"remaining_time":0.3850148996},
{"learn":[0.3466462914],"iteration":975,"passed_time":15.04496482,"remaining_time":0.3699581513},
{"learn":[0.3466199439],"iteration":976,"passed_time":15.06149238,"remaining_time":0.3545694215},
{"learn":[0.3466122101],"iteration":977,"passed_time":15.08508365,"remaining_time":0.3393372601},
{"learn":[0.3465890542],"iteration":978,"passed_time":15.10553706,"remaining_time":0.3240207132},
{"learn":[0.3465750173],"iteration":979,"passed_time":15.13052911,"remaining_time":0.3087863084},
{"learn":[0.3465631435],"iteration":980,"passed_time":15.16036101,"remaining_time":0.2936257485},
{"learn":[0.3465574865],"iteration":981,"passed_time":15.18873434,"remaining_time":0.2784085725},
{"learn":[0.3465282061],"iteration":982,"passed_time":15.2110824,"remaining_time":0.2630604282},
{"learn":[0.3465073114],"iteration":983,"passed_time":15.24147901,"remaining_time":0.247828927},
{"learn":[0.3464681361],"iteration":984,"passed_time":15.26670157,"remaining_time":0.2324878412},
{"learn":[0.3464558603],"iteration":985,"passed_time":15.27932931,"remaining_time":0.2169478806},
{"learn":[0.3464461139],"iteration":986,"passed_time":15.29780233,"remaining_time":0.2014908108},
{"learn":[0.3464446128],"iteration":987,"passed_time":15.31628035,"remaining_time":0.1860276966},
{"learn":[0.3464303537],"iteration":988,"passed_time":15.33036774,"remaining_time":0.1705096513},
{"learn":[0.3464077071],"iteration":989,"passed_time":15.35090815,"remaining_time":0.1550596783},
{"learn":[0.3463897022],"iteration":990,"passed_time":15.37086907,"remaining_time":0.1395941692},
{"learn":[0.3463657948],"iteration":991,"passed_time":15.38810905,"remaining_time":0.1240976536},
{"learn":[0.3463473067],"iteration":992,"passed_time":15.42757292,"remaining_time":0.1087542905},
{"learn":[0.3463413977],"iteration":993,"passed_time":15.46090379,"remaining_time":0.09332537496},
{"learn":[0.346336467],"iteration":994,"passed_time":15.49532615,"remaining_time":0.07786596054},
{"learn":[0.3463191618],"iteration":995,"passed_time":15.52993759,"remaining_time":0.06236922728},
{"learn":[0.3462847678],"iteration":996,"passed_time":15.56476273,"remaining_time":0.04683479258},
{"learn":[0.346260141],"iteration":997,"passed_time":15.61864681,"remaining_time":0.03129989341},
{"learn":[0.3462308981],"iteration":998,"passed_time":15.64365303,"remaining_time":0.01565931234},
{"learn":[0.3462111075],"iteration":999,"passed_time":15.66596624,"remaining_time":0}
]}